[
  {
    "key": "MDAID_旅先の愛の祭の花飾り",
    "value": "旅地愛之祭典的花飾"
  },
  {
    "key": "MDAID_H_旅先の愛の祭の花飾り",
    "value": "在英雄們的雙人之旅中戰勝BOSS的證明。\n充滿旅行回憶的物品。"
  },
  {
    "key": "MID_MISSION_S202602HERO01_TITLE",
    "value": "大英雄戰"
  },
  {
    "key": "MID_MISSION_S202602HERO01_A1",
    "value": "特殊:突破歡愉的痛楚孤慄"
  },
  {
    "key": "MID_MISSION_H_S202602HERO01_A1",
    "value": "將亞斯克王國的王子阿爾馮斯編入我軍，\n過關大英雄戰・歡愉的痛楚孤慄。"
  },
  {
    "key": "MID_MISSION_S202602HERO01_A2",
    "value": "特殊:突破歡愉的痛楚孤慄"
  },
  {
    "key": "MID_MISSION_H_S202602HERO01_A2",
    "value": "將歡愉的痛楚孤慄編入我軍，\n過關大英雄戰・歡愉的痛楚孤慄(超難以上)。"
  },
  {
    "key": "MID_MISSION_S202602HERO01_A3",
    "value": "特殊:擊敗歡愉的痛楚孤慄"
  },
  {
    "key": "MID_MISSION_H_S202602HERO01_A3",
    "value": "以亞斯克王國的王子阿爾馮斯\n擊敗等級40以上的歡愉的痛楚孤慄。"
  },
  {
    "key": "MID_MISSION_S202602HERO01_A4",
    "value": "特殊:擊敗歡愉的痛楚孤慄"
  },
  {
    "key": "MID_MISSION_H_S202602HERO01_A4",
    "value": "以歡愉的痛楚孤慄\n擊敗等級40以上的歡愉的痛楚孤慄。"
  },
  {
    "key": "MID_MISSION_S202602HERO01_A5",
    "value": "特殊:突破歡愉的痛楚孤慄"
  },
  {
    "key": "MID_MISSION_H_S202602HERO01_A5",
    "value": "我軍全員為飛行，\n過關大英雄戰・歡愉的痛楚孤慄(超難以上)。"
  },
  {
    "key": "MID_MISSION_S202602JOURNEY01_TITLE",
    "value": "英雄們的雙人之旅"
  },
  {
    "key": "MID_MISSION_S202602JOURNEY01_A1",
    "value": "過關英雄們的雙人之旅"
  },
  {
    "key": "MID_MISSION_H_S202602JOURNEY01_A1",
    "value": "過關英雄們的雙人之旅。"
  },
  {
    "key": "MID_MISSION_S202602JOURNEY01_A2",
    "value": "過關英雄們的雙人之旅"
  },
  {
    "key": "MID_MISSION_H_S202602JOURNEY01_A2",
    "value": "過關英雄們的雙人之旅。"
  },
  {
    "key": "MID_MISSION_S202602SUBSC02_TITLE",
    "value": "FEH PASS限定"
  },
  {
    "key": "MID_MISSION_S202602SUBSC02_A1",
    "value": "擊敗敵人"
  },
  {
    "key": "MID_MISSION_H_S202602SUBSC02_A1",
    "value": "擊敗敵人。"
  },
  {
    "key": "MID_MISSION_S202602SUBSC02_A2",
    "value": "擊敗敵人"
  },
  {
    "key": "MID_MISSION_H_S202602SUBSC02_A2",
    "value": "擊敗敵人。"
  },
  {
    "key": "MID_MISSION_S202602SUBSC02_A3",
    "value": "在鬥技場獲勝"
  },
  {
    "key": "MID_MISSION_H_S202602SUBSC02_A3",
    "value": "在鬥技場獲勝。"
  },
  {
    "key": "MID_MISSION_S202602SUBSC02_A4",
    "value": "在鬥技場獲勝"
  },
  {
    "key": "MID_MISSION_H_S202602SUBSC02_A4",
    "value": "在鬥技場獲勝。"
  },
  {
    "key": "MID_MISSION_S202602SUBSC02_A5",
    "value": "擊敗重裝"
  },
  {
    "key": "MID_MISSION_H_S202602SUBSC02_A5",
    "value": "擊敗重裝的敵人。"
  },
  {
    "key": "MID_MISSION_S202602SUBSC02_A6",
    "value": "擊敗飛行"
  },
  {
    "key": "MID_MISSION_H_S202602SUBSC02_A6",
    "value": "擊敗飛行的敵人。"
  },
  {
    "key": "MID_MISSION_S202602VSWEAPON01_TITLE",
    "value": "來自魔道的挑戰"
  },
  {
    "key": "MID_MISSION_S202602VSWEAPON01_A1",
    "value": "以槍擊敗赤魔"
  },
  {
    "key": "MID_MISSION_H_S202602VSWEAPON01_A1",
    "value": "以槍的我方擊敗武器為赤魔的敵人。"
  },
  {
    "key": "MID_MISSION_S202602VSWEAPON01_A2",
    "value": "以青魔擊敗赤魔"
  },
  {
    "key": "MID_MISSION_H_S202602VSWEAPON01_A2",
    "value": "以青魔的我方擊敗武器為赤魔的敵人。"
  },
  {
    "key": "MID_MISSION_S202602VSWEAPON01_A3",
    "value": "以斧擊敗青魔"
  },
  {
    "key": "MID_MISSION_H_S202602VSWEAPON01_A3",
    "value": "以斧的我方擊敗武器為青魔的敵人。"
  },
  {
    "key": "MID_MISSION_S202602VSWEAPON01_A4",
    "value": "以綠魔擊敗青魔"
  },
  {
    "key": "MID_MISSION_H_S202602VSWEAPON01_A4",
    "value": "以綠魔的我方擊敗武器為青魔的敵人。"
  },
  {
    "key": "MID_MISSION_S202602VSWEAPON01_A5",
    "value": "以劍擊敗綠魔"
  },
  {
    "key": "MID_MISSION_H_S202602VSWEAPON01_A5",
    "value": "以劍的我方擊敗武器為綠魔的敵人。"
  },
  {
    "key": "MID_MISSION_S202602VSWEAPON01_A6",
    "value": "以赤魔擊敗綠魔"
  },
  {
    "key": "MID_MISSION_H_S202602VSWEAPON01_A6",
    "value": "以赤魔的我方擊敗武器為綠魔的敵人。"
  },
  {
    "key": "MID_MISSION_S202602VSWEAPON01_A7",
    "value": "以無屬性弓擊敗赤魔"
  },
  {
    "key": "MID_MISSION_H_S202602VSWEAPON01_A7",
    "value": "以無屬性弓的我方擊敗武器為赤魔的敵人。"
  },
  {
    "key": "MID_MISSION_S202602VSWEAPON01_A8",
    "value": "以無屬性暗器擊敗青魔"
  },
  {
    "key": "MID_MISSION_H_S202602VSWEAPON01_A8",
    "value": "以無屬性暗器的我方擊敗武器為青魔的敵人。"
  },
  {
    "key": "MID_MISSION_S202602VSWEAPON01_A9",
    "value": "以杖擊敗綠魔"
  },
  {
    "key": "MID_MISSION_H_S202602VSWEAPON01_A9",
    "value": "以杖的我方擊敗武器為綠魔的敵人。"
  },
  {
    "key": "MID_MISSION_S202602VSWEAPON01_A10",
    "value": "以青屬性擊敗赤魔"
  },
  {
    "key": "MID_MISSION_H_S202602VSWEAPON01_A10",
    "value": "以青屬性的我方擊敗武器為赤魔的敵人。"
  },
  {
    "key": "MID_MISSION_S202602VSWEAPON01_A11",
    "value": "以綠屬性擊敗青魔"
  },
  {
    "key": "MID_MISSION_H_S202602VSWEAPON01_A11",
    "value": "以綠屬性的我方擊敗武器為青魔的敵人。"
  },
  {
    "key": "MID_MISSION_S202602VSWEAPON01_A12",
    "value": "以赤屬性擊敗綠魔"
  },
  {
    "key": "MID_MISSION_H_S202602VSWEAPON01_A12",
    "value": "以赤屬性的我方擊敗武器為綠魔的敵人。"
  },
  {
    "key": "MID_MISSION_S202602VSWEAPON01_A13",
    "value": "擊敗赤魔"
  },
  {
    "key": "MID_MISSION_H_S202602VSWEAPON01_A13",
    "value": "擊敗武器為赤魔的敵人。"
  },
  {
    "key": "MID_MISSION_S202602VSWEAPON01_A14",
    "value": "擊敗青魔"
  },
  {
    "key": "MID_MISSION_H_S202602VSWEAPON01_A14",
    "value": "擊敗武器為青魔的敵人。"
  },
  {
    "key": "MID_MISSION_S202602VSWEAPON01_A15",
    "value": "擊敗綠魔"
  },
  {
    "key": "MID_MISSION_H_S202602VSWEAPON01_A15",
    "value": "擊敗武器為綠魔的敵人。"
  },
  {
    "key": "MID_MISSION_W_S202602STORY_C01_TITLE",
    "value": "冰神尼福爾"
  },
  {
    "key": "MID_MISSION_W_S202602STORY_C01_A1",
    "value": "特殊:突破第4章-第1節(超難)"
  },
  {
    "key": "MID_MISSION_H_W_S202602STORY_C01_A1",
    "value": "我軍內有成員武器為斧，\n且在4人皆生存的狀態下\n過關<第10部>第4章-第1節(超難)。\n(出擊時，雙人組合的後衛角色不列入計算)"
  },
  {
    "key": "MID_MISSION_W_S202602STORY_C01_A2",
    "value": "特殊:突破第4章-第2節(超難)"
  },
  {
    "key": "MID_MISSION_H_W_S202602STORY_C01_A2",
    "value": "我軍內有成員武器為劍，\n且在4人皆生存的狀態下\n過關<第10部>第4章-第2節(超難)。\n(出擊時，雙人組合的後衛角色不列入計算)"
  },
  {
    "key": "MID_MISSION_W_S202602STORY_C01_A3",
    "value": "特殊:突破第4章-第3節(超難)"
  },
  {
    "key": "MID_MISSION_H_W_S202602STORY_C01_A3",
    "value": "我軍內有成員武器為槍，\n且在4人皆生存的狀態下\n過關<第10部>第4章-第3節(超難)。\n(出擊時，雙人組合的後衛角色不列入計算)"
  },
  {
    "key": "MID_MISSION_W_S202602STORY_C01_A4",
    "value": "特殊:突破第4章-第4節(超難)"
  },
  {
    "key": "MID_MISSION_H_W_S202602STORY_C01_A4",
    "value": "我軍內有成員武器為斧，\n且在4人皆生存的狀態下\n過關<第10部>第4章-第4節(超難)。\n(出擊時，雙人組合的後衛角色不列入計算)"
  },
  {
    "key": "MID_MISSION_W_S202602STORY_C01_A5",
    "value": "特殊:突破第4章-第5節(超難)"
  },
  {
    "key": "MID_MISSION_H_W_S202602STORY_C01_A5",
    "value": "我軍內有成員武器為劍，\n且在4人皆生存的狀態下\n過關<第10部>第4章-第5節(超難)。\n(出擊時，雙人組合的後衛角色不列入計算)"
  },
  {
    "key": "MPID_双界総選挙ヘクトル",
    "value": "海克托爾"
  },
  {
    "key": "MPID_SEARCH_双界総選挙ヘクトル",
    "value": "海克托爾"
  },
  {
    "key": "MPID_双界総選挙セリカ",
    "value": "賽莉卡"
  },
  {
    "key": "MPID_SEARCH_双界総選挙セリカ",
    "value": "賽莉卡"
  },
  {
    "key": "MPID_救世フィヨルム",
    "value": "菲約爾姆"
  },
  {
    "key": "MPID_SEARCH_救世フィヨルム",
    "value": "菲約爾姆"
  },
  {
    "key": "MPID_HONOR_双界総選挙ヘクトル",
    "value": "無所畏懼的突進"
  },
  {
    "key": "MPID_HONOR_双界総選挙セリカ",
    "value": "高尚的公主們"
  },
  {
    "key": "MPID_HONOR_救世フィヨルム",
    "value": "寄宿著冰之力的公主"
  },
  {
    "key": "MPID_H_双界総選挙ヘクトル",
    "value": "海克托爾和艾夫拉姆，兩位血氣方剛的年輕人\n在戰鬥之中找出人們、兄長及父親活過的意義。\n（登場作品：\n　『ファイアーエムブレム　烈火の剣・聖魔の光石』）"
  },
  {
    "key": "MPID_H_双界総選挙セリカ",
    "value": "賽莉卡和維洛妮卡，年紀輕輕便身負國家命運的\n她們在歷史洪流中飄搖，依然憑自己的意志向前。\n（登場作品：\n　『ファイアーエムブレム　Echoes・Heroes』）"
  },
  {
    "key": "MPID_H_救世フィヨルム",
    "value": "冰之王國尼福爾的第二公主。溫柔的少女。\n以冰神尼福爾賜予的力量為拯救世界而戰。"
  },
  {
    "key": "MPID_VOICE_双界総選挙ヘクトル",
    "value": "鳥海浩輔(Kohsuke Toriumi) with 八代拓(Taku Yashiro)"
  },
  {
    "key": "MPID_VOICE_双界総選挙セリカ",
    "value": "東山奈央(Nao Toyama) with 日高里菜(Rina Hidaka)"
  },
  {
    "key": "MPID_VOICE_救世フィヨルム",
    "value": "高橋李依(Rie Takahashi)"
  },
  {
    "key": "MPID_VOICE_プリシラEX01",
    "value": "橋本ちなみ(Chinami Hashimoto)"
  },
  {
    "key": "MPID_ILLUST_双界総選挙ヘクトル",
    "value": "kuren"
  },
  {
    "key": "MPID_ILLUST_双界総選挙セリカ",
    "value": "azuタロウ(azu‐taro)"
  },
  {
    "key": "MPID_ILLUST_救世フィヨルム",
    "value": "前嶋重機(Shigeki Maeshima)"
  },
  {
    "key": "MPID_ILLUST_プリシラEX01",
    "value": "nima"
  },
  {
    "key": "MPID_LEGEND_双界総選挙ヘクトル",
    "value": "（雙界技能可在地圖中使用１次。\n　只要按下「雙界按鈕」即可使用。\n　若自身處於雙人組合狀態時，則無法使用）\n（若持有可使用戰法的技能或狀態，\n　則在自己可進行行動時「連翼技能」及「雙界技能」\n　將無法使用（若為已行動狀態則可使用））\n\n雙界效果：「烈火の剣」「聖魔の光石」\n「跨越雙界」中的得分上升\n（※詳情記載於「跨越雙界」內的說明）"
  },
  {
    "key": "MPID_LEGEND_双界総選挙セリカ",
    "value": "（雙界技能可在地圖中使用１次。\n　只要按下「雙界按鈕」即可使用。\n　若自身處於雙人組合狀態時，則無法使用）\n（若持有可使用戰法的技能或狀態，\n　則在自己可進行行動時「連翼技能」及「雙界技能」\n　將無法使用（若為已行動狀態則可使用））\n\n雙界效果：「Echoes」「Heroes」\n「跨越雙界」中的得分上升\n（※詳情記載於「跨越雙界」內的說明）"
  },
  {
    "key": "MID_TIPS_Summon_v1002b_another_01_双界総選挙ヘクトル",
    "value": "偉大的重騎士與雙聖的勇猛王子。\n他們的英勇將震懾敵軍！面對範圍奧義也無所畏懼，\n穩穩擋下遠距離攻擊並進行猛烈反擊！"
  },
  {
    "key": "MID_TIPS_Summon_v1002b_another_01_双界総選挙セリカ",
    "value": "女神的神官戰士與偉大的皇女。高舉的劍\n讓我軍熱血沸騰！透過戰法對距離６格的敵人\n發動強烈的４連擊！以堅定的意志不斷挺身奮戰！"
  },
  {
    "key": "MID_TIPS_Summon_v1002b_another_01_救世フィヨルム",
    "value": "阻止浩劫，為大家帶來溫柔的冬天吧。\n以冰束縛敵人，切換戰法使其無處可逃並將其打倒。\n面對敵人的攻擊也不會退縮，以強大的力量反擊！"
  },
  {
    "key": "MSID_双愛王家の剣",
    "value": "雙愛王家之劍"
  },
  {
    "key": "MSID_SEARCH_双愛王家の剣",
    "value": "雙愛王家之劍"
  },
  {
    "key": "MSID_双勇マルテ",
    "value": "雙勇馬爾堤"
  },
  {
    "key": "MSID_SEARCH_双勇マルテ",
    "value": "雙勇馬爾堤"
  },
  {
    "key": "MSID_氷の救世の槍",
    "value": "冰凍救世之槍"
  },
  {
    "key": "MSID_SEARCH_氷の救世の槍",
    "value": "冰凍救世之槍"
  },
  {
    "key": "MSID_真氷の聖鏡",
    "value": "真冰之聖鏡"
  },
  {
    "key": "MSID_SEARCH_真氷の聖鏡",
    "value": "真冰之聖鏡"
  },
  {
    "key": "MSID_重装の双炎",
    "value": "重裝之雙炎"
  },
  {
    "key": "MSID_SEARCH_重装の双炎",
    "value": "重裝之雙炎"
  },
  {
    "key": "MSID_真オスティアの反撃",
    "value": "真奧斯提亞的反擊"
  },
  {
    "key": "MSID_SEARCH_真オスティアの反撃",
    "value": "真奧斯提亞的反擊"
  },
  {
    "key": "MSID_攻速無欠・鬼没",
    "value": "攻速無缺・鬼沒"
  },
  {
    "key": "MSID_SEARCH_攻速無欠・鬼没",
    "value": "攻速無缺･鬼沒"
  },
  {
    "key": "MSID_真獅子連斬",
    "value": "真獅子連斬"
  },
  {
    "key": "MSID_SEARCH_真獅子連斬",
    "value": "真獅子連斬"
  },
  {
    "key": "MSID_速さ魔防の信念",
    "value": "速度魔防的信心"
  },
  {
    "key": "MSID_SEARCH_速さ魔防の信念",
    "value": "速度魔防的信心"
  },
  {
    "key": "MSID_H_双愛王家の剣",
    "value": "$a容易發動奧義（發動計量－１）\n\n自己和位於自身縱向３列及橫向３列內的我方，\n戰鬥中的攻擊、速度、防守、魔防＋○\n（○的數值為：自己為１５，我方為５），\n抵銷敵人的奧義發動計量變化量＋，\n並抵銷自己的奧義發動計量變化量－，\n自身奧義發動計量變化量＋１\n（若有多個相同系統效果，僅取最大值）\n\n戰鬥中，給予的傷害＋２５（範圍奧義除外），\n所受傷害－１５（範圍奧義除外），\n受到敵人奧義攻擊的傷害再－１５（範圍奧義除外），\n戰鬥後回復ＨＰ７\n\n可使用下述的【戰法】\n―――――【戰法】：霸神斷龍劍―――――\n可攻擊與自己相距３格的敵人（無法攻擊相鄰的敵人）\n\n戰鬥中造成的傷害＋１０（範圍奧義除外）\n\n敵人發動【防護屏障】效果時，無法穿越\n其周圍３格以內的格子（若持有穿越則無效）\n滿足下列任一條件時，將受到反擊\n（條件Ａ：敵人為射程為１格的重裝時\n　條件Ｂ：敵人擁有「可無視距離進行反擊」時）\n戰鬥後移動技能會無效\n技能效果的射程判定視為射程為１\n使用戰法後，２回合內無法使用\n――――――――――――――――――――\n\n【戰法】\n點觸畫面下方的「戰法按鈕」，即可使用戰法\n\n戰法狀態僅在技能持有者行動時有效\n若自身處於雙人組合狀態，\n或裝備多個持有戰法的技能，\n戰法將無效"
  },
  {
    "key": "MSID_H_双愛王家の剣_NOSKW",
    "value": "$a容易發動奧義（發動計量－１）\n\n自己和位於自身縱向３列及橫向３列內的我方，\n戰鬥中的攻擊、速度、防守、魔防＋○\n（○的數值為：自己為１５，我方為５），\n抵銷敵人的奧義發動計量變化量＋，\n並抵銷自己的奧義發動計量變化量－，\n自身奧義發動計量變化量＋１\n（若有多個相同系統效果，僅取最大值）\n\n戰鬥中，給予的傷害＋２５（範圍奧義除外），\n所受傷害－１５（範圍奧義除外），\n受到敵人奧義攻擊的傷害再－１５（範圍奧義除外），\n戰鬥後回復ＨＰ７\n\n可使用下述的【戰法】\n―――――【戰法】：霸神斷龍劍―――――\n可攻擊與自己相距３格的敵人（無法攻擊相鄰的敵人）\n\n戰鬥中造成的傷害＋１０（範圍奧義除外）\n\n敵人發動【防護屏障】效果時，無法穿越\n其周圍３格以內的格子（若持有穿越則無效）\n滿足下列任一條件時，將受到反擊\n（條件Ａ：敵人為射程為１格的重裝時\n　條件Ｂ：敵人擁有「可無視距離進行反擊」時）\n戰鬥後移動技能會無效\n技能效果的射程判定視為射程為１\n使用戰法後，２回合內無法使用\n――――――――――――――――――――"
  },
  {
    "key": "MSID_H_双勇マルテ",
    "value": "容易發動奧義（發動計量－１）\n\n受到的範圍奧義傷害降低８０％\n（巨影的範圍奧義除外）\n\n位於自身縱向３列及橫向３列內的敵人\n戰鬥中的攻擊、速度、防守、魔防－５，\n奧義發動計量變化量－１\n（若有多個相同系統效果，僅取最大值），\n抵銷奧義發動計量變化量＋，\n使奧義相關技能以外的\n「傷害降低◯◯％」效果減少一半\n（計算效果時，小數點後無條件捨去）\n（範圍奧義除外）\n\n戰鬥中的攻擊、速度、防守、魔防＋１０，\n給予的傷害＋２５（範圍奧義除外），\n所受傷害－１５\n（包括範圍奧義（巨影的範圍奧義除外）），\n受到敵人奧義攻擊的傷害再－１５\n（包括範圍奧義（巨影的範圍奧義除外）），\n自己在初次追擊前奧義發動計量－２"
  },
  {
    "key": "MSID_H_氷の救世の槍",
    "value": "$a可發動【再移動（格子間的距離＋１，最大４）】\n容易發動奧義（發動計量－１）\n受到敵人攻擊時，可無視距離進行反擊\n\n我軍回合及敵軍回合開始時，\n賦予自己和周圍２格內的我方【多愁善感】、【迴避】、\n【識破・追擊效果】的效果（１回合）\n\n戰鬥中的攻擊、速度、防守、魔防＋１５，\n給予的傷害＋２５（範圍奧義除外），\n所受傷害－１５（範圍奧義除外），\n受到敵人奧義攻擊的傷害再－１５（範圍奧義除外）\n\n可使用下述的【戰法】\n―――――【戰法】：冰凍救世之槍―――――\n可攻擊與自己相距２格的敵人（無法攻擊相鄰的敵人）\n\n戰鬥中，自己的追擊的速度條件－１０\n\n敵人發動【防護屏障】效果時，無法穿越\n其周圍２格以內的格子（若持有穿越則無效）\n滿足下列任一條件時，將受到反擊\n（條件Ａ：敵人為射程為１格的重裝時\n　條件Ｂ：敵人擁有「可無視距離進行反擊」時\n　條件Ｃ：敵人射程和自己與敵人的距離相同時）\n戰鬥後移動技能會無效\n技能效果的射程判定視為射程為１\n此戰法１回合僅可使用１次\n―――――――――――――――――――――\n\n【再移動（格子間的距離＋１，最大４）】\n由自己發動攻擊、輔助及破壞地形的行動後，\n可馬上移動\n\n可移動的範圍為\n上述行動前的移動前與移動後的格子距離＋１\n（最大４）\n\n【多愁善感】\n戰鬥中的攻擊、速度、防守、魔防提升\n（提升數值為：我軍及敵軍受到的\n　強化以外【有利的狀態】及\n　弱化以外【不利的異常狀態】種類數量）\n（最大７）\n\n【迴避】\n速度高於敵人時，受到的範圍奧義傷害\n以及戰鬥中所受到的攻擊傷害\n降低速度差×４％（最大４０％）\n（巨影的範圍奧義除外）\n\n【識破・追擊效果】\n戰鬥中，速度高於敵人時，\n抵銷敵人擁有的絕對追擊狀態，\n以及自己受到的無法追擊狀態\n\n【戰法】\n點觸畫面下方的「戰法按鈕」，即可使用戰法\n\n戰法狀態僅在技能持有者行動時有效\n若自身處於雙人組合狀態，\n或裝備多個持有戰法的技能，\n戰法將無效"
  },
  {
    "key": "MSID_H_氷の救世の槍_NOSKW",
    "value": "$a可發動【再移動（格子間的距離＋１，最大４）】\n容易發動奧義（發動計量－１）\n受到敵人攻擊時，可無視距離進行反擊\n\n我軍回合及敵軍回合開始時，\n賦予自己和周圍２格內的我方【多愁善感】、【迴避】、\n【識破・追擊效果】的效果（１回合）\n\n戰鬥中的攻擊、速度、防守、魔防＋１５，\n給予的傷害＋２５（範圍奧義除外），\n所受傷害－１５（範圍奧義除外），\n受到敵人奧義攻擊的傷害再－１５（範圍奧義除外）\n\n可使用下述的【戰法】\n―――――【戰法】：冰凍救世之槍―――――\n可攻擊與自己相距２格的敵人（無法攻擊相鄰的敵人）\n\n戰鬥中，自己的追擊的速度條件－１０\n\n敵人發動【防護屏障】效果時，無法穿越\n其周圍２格以內的格子（若持有穿越則無效）\n滿足下列任一條件時，將受到反擊\n（條件Ａ：敵人為射程為１格的重裝時\n　條件Ｂ：敵人擁有「可無視距離進行反擊」時\n　條件Ｃ：敵人射程和自己與敵人的距離相同時）\n戰鬥後移動技能會無效\n技能效果的射程判定視為射程為１\n此戰法１回合僅可使用１次\n―――――――――――――――――――――"
  },
  {
    "key": "MSID_H_真氷の聖鏡",
    "value": "$a發動奧義時，增加速度×６０％的奧義傷害\n\n將戰鬥中受到的攻擊傷害降低４０％\n（範圍奧義除外），\n且一開始受到的攻擊所減輕的傷害值\n將附加至自身下次攻擊\n（僅在本次戰鬥中。\n　因技能產生的減輕效果也包括在減輕的傷害值中）\n\n洛基的棋盤遊戲以外的敵軍回合開始時，\n若地圖上沒有被我軍賦予【天脈・深綠冰】的格子，\n則發動以下２個效果\n・賦予與自己相距２格的格子【天脈・深綠冰】的效果\n　（但以下的格子除外：\n　　・有敵軍的格子\n　　・可破壞地形的格子（天脈以外）\n　　・壓制戰的傳送格子）（１回合）\n・賦予上述被賦予【天脈・深綠冰】的格子以外的\n　自己的格子和周圍３格內的格子\n　　【天脈・深綠】的效果（１回合）\n\n【天脈・深綠冰】\n被賦予此效果的格子會變為以下狀態\n\n敵軍無法進入，可被破壞（ＨＰ１）\n若遭到破壞，會變成【天脈・深綠】\n我軍可進入及待命\n若【天脈・深綠冰】的格子上有我軍，\n對我軍的攻擊將優先於【天脈・深綠冰】的破壞\n\n【天脈・深綠】\n進入被賦予此效果的格子中的對象會受到以下效果\n\n敵人無法透過技能效果從此格子傳送\n或傳送到此格子\n（對持有穿越的敵人無效）\n（可透過壓制戰的據點等其他地形的效果傳送）\n為在此格子中發動再移動的敵人\n附加【再移動限制】的異常狀態（直到敵人下次行動結束）\n\n敵人在戰鬥中的攻擊及速度－５，\n奧義發動計量變化量－１\n（若有多個相同系統效果，僅取最大值），\n且若裝備有在攻擊時發動的奧義，\n戰鬥中，在初次攻擊前奧義發動計量＋１\n（奧義發動計量不會超越最大值）\n\n【再移動限制】\n受到此異常狀態的敵人攻擊射程為１格時，\n發動再移動後可馬上移動的範圍限為最大１格\n敵人攻擊射程為２格時，會在發動再移動後立刻結束行動"
  },
  {
    "key": "MSID_H_真氷の聖鏡_NOSKW",
    "value": "$a發動奧義時，增加速度×６０％的奧義傷害\n\n將戰鬥中受到的攻擊傷害降低４０％\n（範圍奧義除外），\n且一開始受到的攻擊所減輕的傷害值\n將附加至自身下次攻擊\n（僅在本次戰鬥中。\n　因技能產生的減輕效果也包括在減輕的傷害值中）\n\n洛基的棋盤遊戲以外的敵軍回合開始時，\n若地圖上沒有被我軍賦予【天脈・深綠冰】的格子，\n則發動以下２個效果\n・賦予與自己相距２格的格子【天脈・深綠冰】的效果\n　（但以下的格子除外：\n　　・有敵軍的格子\n　　・可破壞地形的格子（天脈以外）\n　　・壓制戰的傳送格子）（１回合）\n・賦予上述被賦予【天脈・深綠冰】的格子以外的\n　自己的格子和周圍３格內的格子\n　　【天脈・深綠】的效果（１回合）"
  },
  {
    "key": "MSID_H_重装の双炎",
    "value": "$a發動奧義時，增加防守數值的奧義傷害\n\n將戰鬥中受到的攻擊傷害降低４０％\n（每次戰鬥能發動兩次，範圍奧義除外）\n\n回合開始時，\n自己的攻擊及防守的【大器】＋２\n\n在發動奧義的戰鬥後，\n自己的攻擊及防守的【大器】＋４\n\n（受此技能影響的【大器】上限為１０）\n\n【大器】\n依【大器】＋○的數值提升指定能力，\n直到地圖結束\n\n（【大器】的提升值\n　不會超越各技能的上限，\n　提升後的能力值上限為９９。\n　不會被視為有利的狀態）"
  },
  {
    "key": "MSID_H_重装の双炎_NOSKW",
    "value": "$a發動奧義時，增加防守數值的奧義傷害\n\n將戰鬥中受到的攻擊傷害降低４０％\n（每次戰鬥能發動兩次，範圍奧義除外）\n\n回合開始時，\n自己的攻擊及防守的【大器】＋２\n\n在發動奧義的戰鬥後，\n自己的攻擊及防守的【大器】＋４\n\n（受此技能影響的【大器】上限為１０）"
  },
  {
    "key": "MSID_H_真オスティアの反撃",
    "value": "ＨＰ＋５、攻擊、速度、防守、魔防＋９\n\n受到敵人攻擊時，可無視距離進行反擊\n\n自己和周圍３格內的我方單位\n戰鬥中抵銷自己受到的無法反擊狀態，\n且受到敵人攻擊時，\n戰鬥中，若可進行追擊，則會在自己攻擊後立刻追擊\n\n戰鬥中，給予的傷害＋７（範圍奧義除外），\n所受傷害－７（範圍奧義除外），\n抵銷自己的奧義發動計量變化量－，\n抵銷敵人的「若可進行追擊，\n則會在自己攻擊後立刻追擊」效果"
  },
  {
    "key": "MSID_H_攻速無欠・鬼没",
    "value": "$a可發動【再移動（格子間的距離＋１，最大４）】\n\n若戰鬥開始時，自身ＨＰ在２５％以上，\n或周圍３格內有我方單位時，\n戰鬥中的攻擊及速度＋９，\n造成的傷害＋７（範圍奧義除外），\n且戰鬥中，速度高於敵人時，\n抵銷敵人擁有的絕對追擊狀態，\n以及自己受到的無法追擊狀態\n\n若戰鬥開始時，自身ＨＰ在２５％以上，\n且周圍３格內有我方單位時，\n戰鬥中的攻擊及速度再＋３\n\n【再移動（格子間的距離＋１，最大４）】\n由自己發動攻擊、輔助及破壞地形的行動後，\n可馬上移動\n\n可移動的範圍為\n上述行動前的移動前與移動後的格子距離＋１\n（最大４）\n\n（透過自己的移動方式移動。\n　例：歩行在林地難以移動）\n（無法攻擊、輔助及破壞地形）\n（若有多個相同系統效果，僅取最大值）\n（１回合僅能發動１次）\n（於行動後立刻發動可再次行動的技能時，\n　若再次行動時滿足再移動的發動條件，即可進行再移動）\n（再移動時可移動的範圍與通常移動的範圍無關）\n（不能傳送到超過再移動距離上限的地方）"
  },
  {
    "key": "MSID_H_攻速無欠・鬼没_NOSKW",
    "value": "$a可發動【再移動（格子間的距離＋１，最大４）】\n\n若戰鬥開始時，自身ＨＰ在２５％以上，\n或周圍３格內有我方單位時，\n戰鬥中的攻擊及速度＋９，\n造成的傷害＋７（範圍奧義除外），\n且戰鬥中，速度高於敵人時，\n抵銷敵人擁有的絕對追擊狀態，\n以及自己受到的無法追擊狀態\n\n若戰鬥開始時，自身ＨＰ在２５％以上，\n且周圍３格內有我方單位時，\n戰鬥中的攻擊及速度再＋３"
  },
  {
    "key": "MSID_H_真獅子連斬",
    "value": "$a攻擊２次（被敵人攻擊時，也可攻擊２次）\n\n回合開始時及\n行動後（發動再移動時則於再移動結束後），\n離自己最近的敵人與其周圍２格內的敵人\n速度及防守－７，\n並附加【弱點暴露】、【混亂】的異常狀態\n（直到敵人下次行動結束）\n\n戰鬥中，敵人的攻擊、速度、防守－５，\n自己給予的傷害＋（速度×２０％）（範圍奧義除外），\n自己所受傷害－（速度×２０％）（範圍奧義除外），\n並當自己在戰鬥中的ＨＰ在２以上，且遭受敵人致命攻擊時，\n將傷害降低至自身ＨＰ會剩下１\n（每次戰鬥僅能發動一次，不可和奧義以外的\n　「遭受敵人致命攻擊時，將傷害降低至\n　自身ＨＰ會剩下１的效果」重複發動）\n\n【弱點暴露】\n受到敵人攻擊時的傷害＋１０\n\n【混亂】\n戰鬥中的攻擊、速度、防守、魔防下降\n（下降數值為：\n　自己和周圍２格內的我方單位當中最高的弱化值）\n（依能力值不同分開計算）"
  },
  {
    "key": "MSID_H_真獅子連斬_NOSKW",
    "value": "$a攻擊２次（被敵人攻擊時，也可攻擊２次）\n\n回合開始時及\n行動後（發動再移動時則於再移動結束後），\n離自己最近的敵人與其周圍２格內的敵人\n速度及防守－７，\n並附加【弱點暴露】、【混亂】的異常狀態\n（直到敵人下次行動結束）\n\n戰鬥中，敵人的攻擊、速度、防守－５，\n自己給予的傷害＋（速度×２０％）（範圍奧義除外），\n自己所受傷害－（速度×２０％）（範圍奧義除外），\n並當自己在戰鬥中的ＨＰ在２以上，且遭受敵人致命攻擊時，\n將傷害降低至自身ＨＰ會剩下１\n（每次戰鬥僅能發動一次，不可和奧義以外的\n　「遭受敵人致命攻擊時，將傷害降低至\n　自身ＨＰ會剩下１的效果」重複發動）"
  },
  {
    "key": "MSID_H_速さ魔防の信念",
    "value": "$a我軍回合及敵軍回合開始時，\n若周圍２格內有我方單位，\n則自己的速度及魔防＋６，\n並賦予【防護屏障】的效果（１回合）\n\n自己被賦予【防護屏障】的效果時，\n戰鬥中的速度及魔防＋４，\n將戰鬥中一開始受到的攻擊和攻擊２次的傷害－５，\n在敵人初次攻擊前，自身奧義發動計量－１\n\n【防護屏障】\n讓攻擊射程為１格的敵人無法穿越\n自己周圍１格以內的格子（對持有穿越的敵人無效）\n\n讓攻擊射程為２格的敵人無法穿越\n自己周圍２格以內的格子（對持有穿越的敵人無效）"
  },
  {
    "key": "MSID_H_速さ魔防の信念_NOSKW",
    "value": "$a我軍回合及敵軍回合開始時，\n若周圍２格內有我方單位，\n則自己的速度及魔防＋６，\n並賦予【防護屏障】的效果（１回合）\n\n自己被賦予【防護屏障】的效果時，\n戰鬥中的速度及魔防＋４，\n將戰鬥中一開始受到的攻擊和攻擊２次的傷害－５，\n在敵人初次攻擊前，自身奧義發動計量－１"
  },
  {
    "key": "MID_CHAPTER_TITLE_C1004",
    "value": "第１０部　第４章"
  },
  {
    "key": "MID_CHAPTER_C1004",
    "value": "冰神尼福爾"
  },
  {
    "key": "MID_STAGE_TITLE_SA041",
    "value": "第４章—第１節"
  },
  {
    "key": "MID_STAGE_TITLE_SA042",
    "value": "第４章—第２節"
  },
  {
    "key": "MID_STAGE_TITLE_SA043",
    "value": "第４章—第３節"
  },
  {
    "key": "MID_STAGE_TITLE_SA044",
    "value": "第４章—第４節"
  },
  {
    "key": "MID_STAGE_TITLE_SA045",
    "value": "第４章—第５節"
  },
  {
    "key": "MID_STAGE_SA041",
    "value": "毀滅三界之人"
  },
  {
    "key": "MID_STAGE_SA042",
    "value": "前往冰之神殿"
  },
  {
    "key": "MID_STAGE_SA043",
    "value": "高尚的公主們"
  },
  {
    "key": "MID_STAGE_SA044",
    "value": "無所畏懼的突進"
  },
  {
    "key": "MID_STAGE_SA045",
    "value": "所謂的心"
  },
  {
    "key": "MID_STAGE_HONOR_T0216",
    "value": "拉切爾　＆"
  },
  {
    "key": "MID_STAGE_T0216",
    "value": "雷納克"
  },
  {
    "key": "MID_CHAPTER_ST_C0A03",
    "value": "第３～４章"
  },
  {
    "key": "MID_STAGE_TITLE_ST_S0A03",
    "value": "第３章"
  },
  {
    "key": "MID_STAGE_TITLE_ST_S0A04",
    "value": "第４章"
  },
  {
    "key": "MID_STAGE_TITLE_ST_S1A04",
    "value": "第３～４章"
  },
  {
    "key": "MID_STAGE_TITLE_PB304",
    "value": "技能篇３０４"
  },
  {
    "key": "MID_STAGE_PB304",
    "value": "偉人現身"
  }
]
