[
  {
    "key": "MID_ENHANCE_FORMAL_HELP_113",
    "value": "存活時，可透過戰鬥或輔助取得２倍ＳＰ\n（若有多個相同系統效果，僅取最大值）\n\n戰鬥中的攻擊、速度、防守、魔防＋５，\n給予的傷害＋７（範圍奧義除外），\n所受傷害－７（範圍奧義除外），\n戰鬥後，奧義發動計量－１\n（１回合）"
  },
  {
    "key": "MID_ENHANCE_HELP_113",
    "value": "２倍ＳＰ，戰鬥力提升＆戰鬥後奧義計量－１"
  },
  {
    "key": "MID_MISSION_S202607HERO01_TITLE",
    "value": "大英雄戰"
  },
  {
    "key": "MID_MISSION_S202607HERO01_A1",
    "value": "特殊:突破達古達"
  },
  {
    "key": "MID_MISSION_H_S202607HERO01_A1",
    "value": "將亞斯克王國的王子阿爾馮斯編入我軍，\n過關大英雄戰・紫龍山的前山賊達古達。"
  },
  {
    "key": "MID_MISSION_S202607HERO01_A2",
    "value": "特殊:突破達古達"
  },
  {
    "key": "MID_MISSION_H_S202607HERO01_A2",
    "value": "將紫龍山的前山賊達古達編入我軍，\n過關大英雄戰・紫龍山的前山賊達古達(超難以上)。"
  },
  {
    "key": "MID_MISSION_S202607HERO01_A3",
    "value": "特殊:擊敗達古達"
  },
  {
    "key": "MID_MISSION_H_S202607HERO01_A3",
    "value": "以亞斯克王國的王子阿爾馮斯\n擊敗等級40以上的紫龍山的前山賊達古達。"
  },
  {
    "key": "MID_MISSION_S202607HERO01_A4",
    "value": "特殊:擊敗達古達"
  },
  {
    "key": "MID_MISSION_H_S202607HERO01_A4",
    "value": "以紫龍山的前山賊達古達\n擊敗等級40以上的紫龍山的前山賊達古達。"
  },
  {
    "key": "MID_MISSION_S202607HERO01_A5",
    "value": "特殊:突破達古達"
  },
  {
    "key": "MID_MISSION_H_S202607HERO01_A5",
    "value": "我軍全員為步行，\n過關大英雄戰・紫龍山的前山賊達古達(超難以上)。"
  },
  {
    "key": "MID_MISSION_S202607MJOLNIR01_TITLE",
    "value": "妙爾尼爾"
  },
  {
    "key": "MID_MISSION_S202607MJOLNIR01_A1",
    "value": "在妙爾尼爾中以我的召喚師擊敗"
  },
  {
    "key": "MID_MISSION_H_S202607MJOLNIR01_A1",
    "value": "在妙爾尼爾中以我的召喚師擊敗敵人。"
  },
  {
    "key": "MID_MISSION_S202607MJOLNIR01_A2",
    "value": "在妙爾尼爾中以我的召喚師擊敗"
  },
  {
    "key": "MID_MISSION_H_S202607MJOLNIR01_A2",
    "value": "在妙爾尼爾中以我的召喚師擊敗敵人。"
  },
  {
    "key": "MID_MISSION_S202607SENKA01_DAILY_TITLE",
    "value": "戰渦連戰"
  },
  {
    "key": "MID_MISSION_S202607SENKA01_DAILY_A1",
    "value": "特殊:突破戰渦連戰"
  },
  {
    "key": "MID_MISSION_H_S202607SENKA01_DAILY_A1",
    "value": "過關戰渦連戰最終地圖。"
  },
  {
    "key": "MID_MISSION_S202607SENKA01_DAILY_A2",
    "value": "特殊:突破戰渦連戰"
  },
  {
    "key": "MID_MISSION_H_S202607SENKA01_DAILY_A2",
    "value": "過關戰渦連戰最終地圖。"
  },
  {
    "key": "MID_MISSION_S202607SENKA01_DAILY_A3",
    "value": "特殊:突破戰渦連戰"
  },
  {
    "key": "MID_MISSION_H_S202607SENKA01_DAILY_A3",
    "value": "過關戰渦連戰最終地圖。"
  },
  {
    "key": "MID_MISSION_S202607SENKA01_DAILY_A4",
    "value": "特殊:突破戰渦連戰"
  },
  {
    "key": "MID_MISSION_H_S202607SENKA01_DAILY_A4",
    "value": "過關戰渦連戰最終地圖。"
  },
  {
    "key": "MID_MISSION_S202607SENKA02_DAILY_TITLE",
    "value": "戰渦連戰"
  },
  {
    "key": "MID_MISSION_S202607SENKA02_DAILY_A1",
    "value": "特殊:突破戰渦連戰"
  },
  {
    "key": "MID_MISSION_H_S202607SENKA02_DAILY_A1",
    "value": "過關戰渦連戰最終地圖。"
  },
  {
    "key": "MID_MISSION_S202607SENKA02_DAILY_A2",
    "value": "特殊:突破戰渦連戰"
  },
  {
    "key": "MID_MISSION_H_S202607SENKA02_DAILY_A2",
    "value": "過關戰渦連戰最終地圖。"
  },
  {
    "key": "MID_MISSION_S202607SENKA02_DAILY_A3",
    "value": "特殊:突破戰渦連戰"
  },
  {
    "key": "MID_MISSION_H_S202607SENKA02_DAILY_A3",
    "value": "過關戰渦連戰最終地圖。"
  },
  {
    "key": "MID_MISSION_S202607SENKA02_DAILY_A4",
    "value": "特殊:突破戰渦連戰"
  },
  {
    "key": "MID_MISSION_H_S202607SENKA02_DAILY_A4",
    "value": "過關戰渦連戰最終地圖。"
  },
  {
    "key": "MID_MISSION_S202607SUBSC01_TITLE",
    "value": "FEH PASS限定"
  },
  {
    "key": "MID_MISSION_S202607SUBSC01_A1",
    "value": "擊敗敵人"
  },
  {
    "key": "MID_MISSION_H_S202607SUBSC01_A1",
    "value": "擊敗敵人。"
  },
  {
    "key": "MID_MISSION_S202607SUBSC01_A2",
    "value": "擊敗敵人"
  },
  {
    "key": "MID_MISSION_H_S202607SUBSC01_A2",
    "value": "擊敗敵人。"
  },
  {
    "key": "MID_MISSION_S202607SUBSC01_A3",
    "value": "在鬥技場獲勝"
  },
  {
    "key": "MID_MISSION_H_S202607SUBSC01_A3",
    "value": "在鬥技場獲勝。"
  },
  {
    "key": "MID_MISSION_S202607SUBSC01_A4",
    "value": "在鬥技場獲勝"
  },
  {
    "key": "MID_MISSION_H_S202607SUBSC01_A4",
    "value": "在鬥技場獲勝。"
  },
  {
    "key": "MID_MISSION_S202607SUBSC01_A5",
    "value": "擊敗重裝"
  },
  {
    "key": "MID_MISSION_H_S202607SUBSC01_A5",
    "value": "擊敗重裝的敵人。"
  },
  {
    "key": "MID_MISSION_S202607SUBSC01_A6",
    "value": "擊敗飛行"
  },
  {
    "key": "MID_MISSION_H_S202607SUBSC01_A6",
    "value": "擊敗飛行的敵人。"
  },
  {
    "key": "MID_MISSION_S202607USEMOVE01_TITLE",
    "value": "騎馬的進擊"
  },
  {
    "key": "MID_MISSION_S202607USEMOVE01_A1",
    "value": "以騎馬擊敗赤屬性"
  },
  {
    "key": "MID_MISSION_H_S202607USEMOVE01_A1",
    "value": "以騎馬的我方擊敗赤屬性的敵人。"
  },
  {
    "key": "MID_MISSION_S202607USEMOVE01_A2",
    "value": "以騎馬擊敗青屬性"
  },
  {
    "key": "MID_MISSION_H_S202607USEMOVE01_A2",
    "value": "以騎馬的我方擊敗青屬性的敵人。"
  },
  {
    "key": "MID_MISSION_S202607USEMOVE01_A3",
    "value": "以騎馬擊敗綠屬性"
  },
  {
    "key": "MID_MISSION_H_S202607USEMOVE01_A3",
    "value": "以騎馬的我方擊敗綠屬性的敵人。"
  },
  {
    "key": "MID_MISSION_S202607USEMOVE01_A4",
    "value": "特殊:以騎馬擊敗"
  },
  {
    "key": "MID_MISSION_H_S202607USEMOVE01_A4",
    "value": "以騎馬的我方擊敗等級20以上武器為劍的敵人。"
  },
  {
    "key": "MID_MISSION_S202607USEMOVE01_A5",
    "value": "特殊:以騎馬擊敗"
  },
  {
    "key": "MID_MISSION_H_S202607USEMOVE01_A5",
    "value": "以騎馬的我方擊敗等級20以上武器為槍的敵人。"
  },
  {
    "key": "MID_MISSION_S202607USEMOVE01_A6",
    "value": "特殊:以騎馬擊敗"
  },
  {
    "key": "MID_MISSION_H_S202607USEMOVE01_A6",
    "value": "以騎馬的我方擊敗等級20以上武器為斧的敵人。"
  },
  {
    "key": "MID_MISSION_S202607USEMOVE01_A7",
    "value": "特殊:以騎馬擊敗"
  },
  {
    "key": "MID_MISSION_H_S202607USEMOVE01_A7",
    "value": "以騎馬的我方擊敗等級20以上武器為無屬性弓的敵人。"
  },
  {
    "key": "MID_MISSION_S202607USEMOVE01_A8",
    "value": "特殊:以騎馬擊敗"
  },
  {
    "key": "MID_MISSION_H_S202607USEMOVE01_A8",
    "value": "以騎馬的我方\n擊敗等級20以上武器為無屬性暗器的敵人。"
  },
  {
    "key": "MID_MISSION_S202607USEMOVE01_A9",
    "value": "特殊:以騎馬擊敗"
  },
  {
    "key": "MID_MISSION_H_S202607USEMOVE01_A9",
    "value": "以騎馬的我方擊敗等級20以上武器為杖的敵人。"
  },
  {
    "key": "MID_MISSION_S202607USEMOVE01_A10",
    "value": "特殊:以騎馬擊敗"
  },
  {
    "key": "MID_MISSION_H_S202607USEMOVE01_A10",
    "value": "以騎馬的我方擊敗等級35以上步行的敵人。"
  },
  {
    "key": "MID_MISSION_S202607USEMOVE01_A11",
    "value": "特殊:以騎馬擊敗"
  },
  {
    "key": "MID_MISSION_H_S202607USEMOVE01_A11",
    "value": "以騎馬的我方擊敗等級35以上騎馬的敵人。"
  },
  {
    "key": "MID_MISSION_S202607USEMOVE01_A12",
    "value": "特殊:以騎馬擊敗"
  },
  {
    "key": "MID_MISSION_H_S202607USEMOVE01_A12",
    "value": "以騎馬的我方擊敗等級35以上重裝的敵人。"
  },
  {
    "key": "MID_MISSION_S202607USEMOVE01_A13",
    "value": "特殊:以騎馬擊敗"
  },
  {
    "key": "MID_MISSION_H_S202607USEMOVE01_A13",
    "value": "以騎馬的我方擊敗等級35以上飛行的敵人。"
  },
  {
    "key": "MID_MISSION_S202607USEMOVE01_A14",
    "value": "特殊:在鬥技場獲勝"
  },
  {
    "key": "MID_MISSION_H_S202607USEMOVE01_A14",
    "value": "我軍內有騎馬成員，在鬥技場獲勝。"
  },
  {
    "key": "MID_MISSION_W_S202607STORY_P01_TITLE",
    "value": "兩人的運動祭"
  },
  {
    "key": "MID_MISSION_W_S202607STORY_P01_A1",
    "value": "特殊:突破外傳126-1節(超難)"
  },
  {
    "key": "MID_MISSION_H_W_S202607STORY_P01_A1",
    "value": "我軍內有成員武器為槍，\n且在4人皆生存的狀態下\n過關外傳126-1節(超難)。\n(出擊時，雙人組合的後衛角色不列入計算)"
  },
  {
    "key": "MID_MISSION_W_S202607STORY_P01_A2",
    "value": "特殊:突破外傳126-2節(超難)"
  },
  {
    "key": "MID_MISSION_H_W_S202607STORY_P01_A2",
    "value": "我軍內有成員武器為斧，\n且在4人皆生存的狀態下\n過關外傳126-2節(超難)。\n(出擊時，雙人組合的後衛角色不列入計算)"
  },
  {
    "key": "MID_MISSION_W_S202607STORY_P01_A3",
    "value": "特殊:突破外傳126-3節(超難)"
  },
  {
    "key": "MID_MISSION_H_W_S202607STORY_P01_A3",
    "value": "我軍內有成員武器為劍，\n且在4人皆生存的狀態下\n過關外傳126-3節(超難)。\n(出擊時，雙人組合的後衛角色不列入計算)"
  },
  {
    "key": "MID_MUSIC_NAME_BGM_MNS_FE14_22",
    "value": "享樂之都"
  },
  {
    "key": "MID_MUSIC_NAME_BGM_MNS_FE15_18",
    "value": "晦冥"
  },
  {
    "key": "MPID_双界ベレス",
    "value": "貝雷絲"
  },
  {
    "key": "MPID_SEARCH_双界ベレス",
    "value": "貝雷絲"
  },
  {
    "key": "MPID_運動着アイク",
    "value": "艾克"
  },
  {
    "key": "MPID_SEARCH_運動着アイク",
    "value": "艾克"
  },
  {
    "key": "MPID_運動着エイクス",
    "value": "艾克米爾尼爾"
  },
  {
    "key": "MPID_SEARCH_運動着エイクス",
    "value": "艾克米爾尼爾"
  },
  {
    "key": "MPID_運動着サーリャ",
    "value": "撒拉"
  },
  {
    "key": "MPID_SEARCH_運動着サーリャ",
    "value": "撒拉"
  },
  {
    "key": "MEID_グロア",
    "value": "古蘿婭"
  },
  {
    "key": "MPID_HONOR_双界ベレス",
    "value": "將打氣化為力量"
  },
  {
    "key": "MPID_HONOR_運動着アイク",
    "value": "全力奔跑的傭兵"
  },
  {
    "key": "MPID_HONOR_運動着エイクス",
    "value": "肌肉的引領者"
  },
  {
    "key": "MPID_HONOR_運動着サーリャ",
    "value": "陰沉的啦啦隊員"
  },
  {
    "key": "MEID_HONOR_グロア",
    "value": "來自未來的女兒"
  },
  {
    "key": "MPID_H_双界ベレス",
    "value": "身為老師的貝雷絲與身為公主的神威攜手合作，\n全力炒熱運動祭的氣氛。\n（登場作品：\n　『FIRE EMBLEM　風花雪月・ｉｆ』）"
  },
  {
    "key": "MPID_H_運動着アイク",
    "value": "格萊爾傭兵團的團長。\n在運動祭挑戰各種各樣的競技。\n（登場作品：『ファイアーエムブレム　蒼炎の軌跡』）"
  },
  {
    "key": "MPID_H_運動着エイクス",
    "value": "世界樹尤克特拉希爾的【治癒者】。\n在運動祭以指導者的身分鍛鍊英雄們。"
  },
  {
    "key": "MPID_H_運動着サーリャ",
    "value": "佩萊吉亞的咒術師。\n在不習慣的陽光之下參與運動祭為人打氣。\n（登場作品：『ファイアーエムブレム　覚醒』）"
  },
  {
    "key": "MEID_H_グロア",
    "value": "來自未來的塞慈之女。為了找到雙胞胎妹妹\n阿爾溫格，向現在的塞慈尋求協助。"
  },
  {
    "key": "MPID_VOICE_双界ベレス",
    "value": "伊藤静(Shizuka Itoh) with 佐藤聡美(Satomi Sato)"
  },
  {
    "key": "MPID_VOICE_運動着アイク",
    "value": "萩道彦(Michihiko Hagi)"
  },
  {
    "key": "MPID_VOICE_運動着エイクス",
    "value": "武内駿輔(Shunsuke Takeuchi)"
  },
  {
    "key": "MPID_VOICE_運動着サーリャ",
    "value": "高田憂希(Yuuki Takada)"
  },
  {
    "key": "MEID_VOICE_グロア",
    "value": "島袋美由利(Miyuri Shimabukuro)"
  },
  {
    "key": "MPID_VOICE_伝承ヘクトルEX01",
    "value": "鳥海浩輔(Kohsuke Toriumi)"
  },
  {
    "key": "MPID_ILLUST_双界ベレス",
    "value": "かかげ(Kakage)"
  },
  {
    "key": "MPID_ILLUST_運動着アイク",
    "value": "kiyu / Trys Inc."
  },
  {
    "key": "MPID_ILLUST_運動着エイクス",
    "value": "P-POCO"
  },
  {
    "key": "MPID_ILLUST_運動着サーリャ",
    "value": "煎茶(Sencha)"
  },
  {
    "key": "MEID_ILLUST_グロア",
    "value": "ひと和(Hitowa)"
  },
  {
    "key": "MPID_ILLUST_伝承ヘクトルEX01",
    "value": "ダイエクスト(DAI-XT.)"
  },
  {
    "key": "MPID_LEGEND_双界ベレス",
    "value": "（雙界技能可在地圖中使用１次。\n　只要按下「雙界按鈕」即可使用。\n　若自身處於雙人組合狀態時，則無法使用）\n（若持有可使用戰法的技能或狀態，\n　則在自己可進行行動時「連翼技能」及「雙界技能」\n　將無法使用（若為已行動狀態則可使用））\n\n雙界效果：「風花雪月」「ｉｆ」\n「跨越雙界」中的得分上升\n（※詳情記載於「跨越雙界」內的說明）"
  },
  {
    "key": "MID_TIPS_Summon_v1007a_summer_01_双界ベレス",
    "value": "在運動祭為人打氣的兩人共織情誼。以戰法及\n再移動於敵營布陣，透過先發制人進行反擊，\n接連橫掃來襲的敵人！還能幫助夥伴成長。"
  },
  {
    "key": "MID_TIPS_Summon_v1007a_summer_01_運動着サーリャ",
    "value": "加油～☆加油～☆……幹嘛用那種眼神看我。\n以詛咒之力強化我方，全軍突擊！自己和夥伴\n都可連續發動奧義，讓敵人全員一路好走……"
  },
  {
    "key": "MID_TIPS_Summon_v1007a_summer_01_運動着アイク",
    "value": "無論是怎樣的比賽，我都會全力以赴。\n承受敵人的所有攻擊並施展破壞力超群的奧義！\n我軍的士氣會隨著每次戰鬥提升！"
  },
  {
    "key": "MID_TIPS_Summon_v1007a_summer_01_運動着エイクス",
    "value": "相信鍛鍊出來的肌肉吧。努力不會背叛自己。\n鍛鍊並提升我軍的強化值，奧義計量也會\n更容易加速。不會讓敵人奪走有利的狀態！"
  },
  {
    "key": "MID_TIPS_Summon_v1007a_summer_10_伝承ギネヴィア",
    "value": "為了祖國伯爾尼以及國民的未來。\n透過「火焰紋章」大幅強化我軍全員！\n克制魔法的敵人＆以先發制人進行反擊將其壓制！"
  },
  {
    "key": "MID_TIPS_Summon_v1007a_summer_11_神階ヘイズ",
    "value": "華納的女神。身上寄宿著黃金魔女的詛咒。\n經過一定回合數後，可透過輔助技能發動\n時間之門！將我軍送上前線，發動猛烈的攻擊！"
  },
  {
    "key": "MSID_第108迷宮の覇者1",
    "value": "第108迷宮的霸王１"
  },
  {
    "key": "MSID_SEARCH_第108迷宮の覇者1",
    "value": "第108迷宮的霸王1"
  },
  {
    "key": "MSID_第108迷宮の覇者2",
    "value": "第108迷宮的霸王２"
  },
  {
    "key": "MSID_SEARCH_第108迷宮の覇者2",
    "value": "第108迷宮的霸王2"
  },
  {
    "key": "MSID_第108迷宮の覇者3",
    "value": "第108迷宮的霸王３"
  },
  {
    "key": "MSID_SEARCH_第108迷宮の覇者3",
    "value": "第108迷宮的霸王3"
  },
  {
    "key": "MSID_豪傑の大斧",
    "value": "豪傑的大斧"
  },
  {
    "key": "MSID_SEARCH_豪傑の大斧",
    "value": "豪傑的大斧"
  },
  {
    "key": "MSID_乱世の斧",
    "value": "亂世之斧"
  },
  {
    "key": "MSID_SEARCH_乱世の斧",
    "value": "亂世之斧"
  },
  {
    "key": "MSID_黄金の蛇・神",
    "value": "黃金蛇・神"
  },
  {
    "key": "MSID_SEARCH_黄金の蛇・神",
    "value": "黃金蛇･神"
  },
  {
    "key": "MSID_新たなるベル…・承",
    "value": "嶄新的伯爾……・承"
  },
  {
    "key": "MSID_SEARCH_新たなるベル…・承",
    "value": "嶄新的伯爾……･承"
  },
  {
    "key": "MSID_グロア",
    "value": "古蘿婭"
  },
  {
    "key": "MSID_SEARCH_グロア",
    "value": "古蘿婭"
  },
  {
    "key": "MSID_グレイル傭兵団の旗",
    "value": "格萊爾傭兵團之旗"
  },
  {
    "key": "MSID_SEARCH_グレイル傭兵団の旗",
    "value": "格萊爾傭兵團之旗"
  },
  {
    "key": "MSID_教え導く師の槍",
    "value": "教導引領的教師之槍"
  },
  {
    "key": "MSID_SEARCH_教え導く師の槍",
    "value": "教導引領的教師之槍"
  },
  {
    "key": "MSID_物陰からのバトン",
    "value": "陰沉之人的指揮棒"
  },
  {
    "key": "MSID_SEARCH_物陰からのバトン",
    "value": "陰沉之人的指揮棒"
  },
  {
    "key": "MSID_運動する体の角",
    "value": "運動身體之角"
  },
  {
    "key": "MSID_SEARCH_運動する体の角",
    "value": "運動身體之角"
  },
  {
    "key": "MSID_真天刻の拍動",
    "value": "真天刻之脈動"
  },
  {
    "key": "MSID_SEARCH_真天刻の拍動",
    "value": "真天刻之脈動"
  },
  {
    "key": "MSID_正真蒼炎の天空",
    "value": "純正蒼炎天空"
  },
  {
    "key": "MSID_SEARCH_正真蒼炎の天空",
    "value": "純正蒼炎天空"
  },
  {
    "key": "MSID_真肉体の咆哮",
    "value": "真肉體的咆哮"
  },
  {
    "key": "MSID_SEARCH_真肉体の咆哮",
    "value": "真肉體的咆哮"
  },
  {
    "key": "MSID_真あの世行きよ…",
    "value": "真一路好走……"
  },
  {
    "key": "MSID_SEARCH_真あの世行きよ…",
    "value": "真一路好走……"
  },
  {
    "key": "MSID_合気・強化無効",
    "value": "合氣・強化無效"
  },
  {
    "key": "MSID_SEARCH_合気・強化無効",
    "value": "合氣･強化無效"
  },
  {
    "key": "MSID_追撃の鼓動・術策",
    "value": "追擊之躍動・術策"
  },
  {
    "key": "MSID_SEARCH_追撃の鼓動・術策",
    "value": "追擊之躍動･術策"
  },
  {
    "key": "MSID_攻速信念・弱化無効",
    "value": "攻速信心・弱化無效"
  },
  {
    "key": "MSID_SEARCH_攻速信念・弱化無効",
    "value": "攻速信心･弱化無效"
  },
  {
    "key": "MSID_守魔信念・弱化無効",
    "value": "防魔信心・弱化無效"
  },
  {
    "key": "MSID_SEARCH_守魔信念・弱化無効",
    "value": "防魔信心･弱化無效"
  },
  {
    "key": "MSID_雇われ魔道士の書R",
    "value": "受雇魔道士之書"
  },
  {
    "key": "MSID_SEARCH_雇われ魔道士の書R",
    "value": "受雇魔道士之書"
  },
  {
    "key": "MSID_H_第108迷宮の覇者1",
    "value": "攻擊、速度、魔防＋２"
  },
  {
    "key": "MSID_H_第108迷宮の覇者2",
    "value": "攻擊、速度、魔防＋３"
  },
  {
    "key": "MSID_H_第108迷宮の覇者3",
    "value": "攻擊、速度、魔防＋４"
  },
  {
    "key": "MSID_H_豪傑の大斧",
    "value": "自己和位於自身縱向３列及橫向３列內的我方，\n戰鬥中的攻擊、速度、防守、魔防＋５，\n抵銷敵人的奧義發動計量變化量＋，\n並抵銷自己的奧義發動計量變化量－，\n自身奧義發動計量變化量＋１\n（若有多個相同系統效果，僅取最大值）\n\n戰鬥中抵銷敵人攻擊及防守的＋強化狀態，\n自己所受傷害－１５（範圍奧義除外）"
  },
  {
    "key": "MSID_H_乱世の斧",
    "value": "戰鬥中的攻擊、速度、防守、魔防＋５，\n自己給予的傷害＋２０（範圍奧義除外），\n自身奧義發動計量變化量＋１\n（若有多個相同系統效果，僅取最大值），\n以自己的攻擊給予傷害時，回復ＨＰ７"
  },
  {
    "key": "MSID_H_至光アーリアルR",
    "value": "$a我軍回合及敵軍回合開始時，\n自己和周圍３格內的我方單位\n攻擊、速度、魔防＋６，\n並賦予【火焰紋章】、「抵銷弱化狀態」的效果\n（１回合）\n\n戰鬥中的攻擊、速度、防守、魔防＋１０，\n使敵人奧義相關技能以外的\n「傷害降低◯◯％」效果減少一半\n（計算效果時，小數點後無條件捨去）\n（範圍奧義除外）\n\n若敵人為魔法兵種，自己在戰鬥中的攻擊＋１０，\n且受到敵人攻擊時，可搶先攻擊\n\n【火焰紋章】\n所有移動方式的克制無效\n\n戰鬥中的攻擊、速度、防守、魔防提升\n（提升數值為：自己和周圍２格內的我方單位當中\n　最高的強化值）\n（依能力值不同分開計算），\n將戰鬥中一開始受到的攻擊和攻擊２次的傷害－１０"
  },
  {
    "key": "MSID_H_至光アーリアルR_NOSKW",
    "value": "$a我軍回合及敵軍回合開始時，\n自己和周圍３格內的我方單位\n攻擊、速度、魔防＋６，\n並賦予【火焰紋章】、「抵銷弱化狀態」的效果\n（１回合）\n\n戰鬥中的攻擊、速度、防守、魔防＋１０，\n使敵人奧義相關技能以外的\n「傷害降低◯◯％」效果減少一半\n（計算效果時，小數點後無條件捨去）\n（範圍奧義除外）\n\n若敵人為魔法兵種，自己在戰鬥中的攻擊＋１０，\n且受到敵人攻擊時，可搶先攻擊"
  },
  {
    "key": "MSID_H_ヘイズR",
    "value": "戰鬥中的攻擊、速度、防守、魔防＋１０，\n抵銷敵人擁有的絕對追擊狀態，\n以及自己受到的無法追擊狀態，\n且由自己發動攻擊時，\n戰鬥中，若可進行追擊，則會在自己攻擊後立刻追擊"
  },
  {
    "key": "MSID_H_透き通る玻璃の弓R",
    "value": "$a容易發動奧義（發動計量－１）\n\n我軍回合及敵軍回合開始時，\n自己和周圍２格內的我方單位攻擊及速度＋６，\n並賦予【神速追擊】、【追擊之躍動】的效果（１回合）\n\n戰鬥中的攻擊、速度、防守、魔防＋１０，\n發動【神速追擊：傷害○％】時，\n若○的數值為９９以下，將以１００計算\n\n【神速追擊】\n在追擊的速度條件－２５的狀態下\n滿足追擊的速度條件時\n（不包含絕對追擊、無法追擊），\n戰鬥中發動【神速追擊：傷害○％】\n（○的數值為：自己無攻擊２次\n　且無法追擊時為８０，若非上述情形時則為４０）\n\n【追擊之躍動】\n戰鬥中，自己在初次追擊前奧義發動計量－２\n\n【神速追擊：傷害○％】\n於自己的一般追擊後，立刻發動額外追擊\n透過神速追擊給予的傷害為一般攻擊時的○％\n（自己無法追擊時，將於一般追擊的時間點發動）\n（神速追擊將被視為追擊，\n　會受「傷害降低◯◯％」等效果影響，\n　但不受無法追擊、攻擊２次的效果影響）\n（若有多個相同系統效果，僅取最大值）"
  },
  {
    "key": "MSID_H_透き通る玻璃の弓R_NOSKW",
    "value": "$a容易發動奧義（發動計量－１）\n\n我軍回合及敵軍回合開始時，\n自己和周圍２格內的我方單位攻擊及速度＋６，\n並賦予【神速追擊】、【追擊之躍動】的效果（１回合）\n\n戰鬥中的攻擊、速度、防守、魔防＋１０，\n發動【神速追擊：傷害○％】時，\n若○的數值為９９以下，將以１００計算"
  },
  {
    "key": "MSID_H_ジャハナ王の砂刃R",
    "value": "$a回合開始時及\n行動後（發動再移動時則於再移動結束後），\n離自己最近的敵人與其周圍２格內的敵人\n速度及防守－７，並附加【弱點暴露】、【不和】、\n「抵銷奧義以外的『遭受敵人致命攻擊時，\n　將傷害降低至自身ＨＰ會剩下１』的效果」的異常狀態\n（直到敵人下次行動結束）\n\n戰鬥中的攻擊、速度、防守、魔防＋１０，\n給予的傷害＋２０（包括範圍奧義）\n\n【弱點暴露】\n受到敵人攻擊時的傷害＋１０\n\n【不和】\n戰鬥中的攻擊、速度、防守、魔防下降\n（下降數值為：周圍２格內的我方人數（上限３）＋２）"
  },
  {
    "key": "MSID_H_ジャハナ王の砂刃R_NOSKW",
    "value": "$a回合開始時及\n行動後（發動再移動時則於再移動結束後），\n離自己最近的敵人與其周圍２格內的敵人\n速度及防守－７，並附加【弱點暴露】、【不和】、\n「抵銷奧義以外的『遭受敵人致命攻擊時，\n　將傷害降低至自身ＨＰ會剩下１』的效果」的異常狀態\n（直到敵人下次行動結束）\n\n戰鬥中的攻擊、速度、防守、魔防＋１０，\n給予的傷害＋２０（包括範圍奧義）"
  },
  {
    "key": "MSID_H_雇われ魔道士の書R",
    "value": "和無屬性的敵人戰鬥時，\n自己在三角互克中佔優勢，敵人居劣勢\n\n自己和位於自身縱向３列及橫向３列內的我方，\n戰鬥中的攻擊、速度、防守、魔防＋５，\n給予的傷害＋○（範圍奧義除外）\n（○的數值為：自己為２０，我方為１０），\n自己在初次攻擊前奧義發動計量－１\n\n戰鬥中抵銷自己的奧義發動計量變化量－"
  },
  {
    "key": "MSID_H_豪傑の大斧R",
    "value": "戰鬥中的攻擊、速度、防守、魔防＋５，\n給予的傷害＋２０（範圍奧義除外），必定可進行追擊，\n戰鬥後回復ＨＰ７"
  },
  {
    "key": "MSID_H_乱世の斧R",
    "value": "位於自身縱向３列及橫向３列內的敵人\n戰鬥中的攻擊、速度、防守、魔防－５，\n必定受到追擊，\n且該敵人若受到強化狀態，\n敵人的攻擊、速度、防守、魔防\n將依敵人受到的強化值下降，\n該敵人的戰鬥對手的攻擊、速度、防守、魔防\n則依敵人受到的強化值提升\n（依能力值不同分開計算）\n\n戰鬥中，自己所受傷害－１５\n（範圍奧義除外），\n敵方無法追擊"
  },
  {
    "key": "MSID_H_黄金の蛇・神",
    "value": "$a此技能被視為「支援」\n\n自己和指定目標的攻擊及速度提升\n（提升數值為：回合數×３）（最大９，１回合），\n依照回合數賦予不同狀態\n（・１以上：可發動【再移動（１）】、\n　　並賦予「移動＋１」（不可累計）\n　・２以上：賦予上述狀態再加上\n　　【強化傷害＋】、【速度解放】\n　・３以上：賦予上述狀態再加上\n　　【雙重攻陣】、【時間之門】）\n（１回合），發動上述效果後讓自己可再次行動\n（強化以外的狀態之賦予及可再次行動的效果\n　１回合僅能發動１次）\n\n可穿過敵方所在的格子\n\n戰鬥中，自己的強化狀態合計值為０時，\n造成的傷害＋○（範圍奧義除外）\n（○的數值為：地圖上\n　被賦予【強化傷害＋】的我方單位當中，\n　強化狀態合計值的最高值）\n\n【再移動（１）】\n由自己發動攻擊、輔助及破壞地形的行動後，\n馬上可進行１格以內的移動\n（若有多個相同系統效果，僅取最大值）\n（１回合僅能發動１次）\n\n【強化傷害＋】\n傷害＋自己身上的強化狀態合計值\n\n【速度解放】\n戰鬥中的速度提升\n（提升數值為：自己受到的強化以外\n　【有利的狀態】數量＋４）（最大８）\n\n【雙重攻陣】\n由自己發動攻擊時，\n若周圍１格內有\n被賦予「雙重攻陣」的我方單位（自己除外），\n攻擊２次（１回合，攻擊２次的效果不可累計）\n\n【時間之門】\n周圍４格內的我方單位\n可移動至自己周圍１格以內的格子（１回合）"
  },
  {
    "key": "MSID_H_黄金の蛇・神_NOSKW",
    "value": "$a此技能被視為「支援」\n\n自己和指定目標的攻擊及速度提升\n（提升數值為：回合數×３）（最大９，１回合），\n依照回合數賦予不同狀態\n（・１以上：可發動【再移動（１）】、\n　　並賦予「移動＋１」（不可累計）\n　・２以上：賦予上述狀態再加上\n　　【強化傷害＋】、【速度解放】\n　・３以上：賦予上述狀態再加上\n　　【雙重攻陣】、【時間之門】）\n（１回合），發動上述效果後讓自己可再次行動\n（強化以外的狀態之賦予及可再次行動的效果\n　１回合僅能發動１次）\n\n可穿過敵方所在的格子\n\n戰鬥中，自己的強化狀態合計值為０時，\n造成的傷害＋○（範圍奧義除外）\n（○的數值為：地圖上\n　被賦予【強化傷害＋】的我方單位當中，\n　強化狀態合計值的最高值）"
  },
  {
    "key": "MSID_H_新たなるベル…・承",
    "value": "$a若有會將魔防差距列入條件的技能，\n則將自身的魔防＋５後再進行比較\n\n自己和位於自身縱向３列及橫向３列內的我方，\n戰鬥中的攻擊、速度、防守、魔防＋５，\n給予的傷害＋７（範圍奧義除外），\n所受傷害－７（範圍奧義除外），\n自己在初次攻擊前奧義發動計量－１，\n戰鬥後回復ＨＰ１０\n\n戰鬥中，自身奧義發動計量變化量＋１\n（若有多個相同系統效果，僅取最大值），\n抵銷敵人擁有的絕對追擊狀態，\n以及自己受到的無法追擊狀態，\n且在追擊的速度條件－１０的狀態下\n滿足追擊的速度條件時\n（不包含絕對追擊、無法追擊），\n戰鬥中發動【神速追擊：傷害１００％】\n\n【神速追擊：傷害１００％】\n於自己的一般追擊後，立刻發動額外追擊\n透過神速追擊給予的傷害為一般攻擊時的１００％\n（自己無法追擊時，將於一般追擊的時間點發動）\n（神速追擊將被視為追擊，\n　會受「傷害降低◯◯％」等效果影響，\n　但不受無法追擊、攻擊２次的效果影響）\n（若有多個相同系統效果，僅取最大值）"
  },
  {
    "key": "MSID_H_新たなるベル…・承_NOSKW",
    "value": "$a若有會將魔防差距列入條件的技能，\n則將自身的魔防＋５後再進行比較\n\n自己和位於自身縱向３列及橫向３列內的我方，\n戰鬥中的攻擊、速度、防守、魔防＋５，\n給予的傷害＋７（範圍奧義除外），\n所受傷害－７（範圍奧義除外），\n自己在初次攻擊前奧義發動計量－１，\n戰鬥後回復ＨＰ１０\n\n戰鬥中，自身奧義發動計量變化量＋１\n（若有多個相同系統效果，僅取最大值），\n抵銷敵人擁有的絕對追擊狀態，\n以及自己受到的無法追擊狀態，\n且在追擊的速度條件－１０的狀態下\n滿足追擊的速度條件時\n（不包含絕對追擊、無法追擊），\n戰鬥中發動【神速追擊：傷害１００％】"
  },
  {
    "key": "MSID_H_グロア",
    "value": "$a可發動【再移動（格子間的距離，最大３、最少１）】\n容易發動奧義（發動計量－１）\n\n行動後（發動再移動時則於再移動結束後），\n為離自己最近的敵人附加【時間陷阱】的異常狀態，\n離自己最近的敵人與其周圍２格內的敵人速度及魔防－７，\n並附加【混亂】、【弱點暴露】的異常狀態\n（直到敵人下次行動結束）\n\n若現在的回合內自己有進行輔助，\n再移動結束後（包含因再移動限制而結束行動的情況），\n讓自己進入可再次行動的狀態，並可再次發動再移動\n（１回合僅能發動１次，\n　在再移動中受到飛空城陷阱的效果時不會發動）\n\n戰鬥中的攻擊、速度、防守、魔防＋１５，\n給予的傷害＋２５（包括範圍奧義），\n所受傷害－１５（範圍奧義除外），\n且由自己發動攻擊時，\n戰鬥中，若可進行追擊，則會在自己攻擊後立刻追擊\n\n【再移動（格子間的距離，最大３、最少１）】\n由自己發動攻擊、輔助及破壞地形的行動後，\n可馬上移動\n\n可移動的範圍為\n上述行動前的移動前與移動後的格子距離\n（最大３、最少１（傳送時也為最少１））\n\n【時間陷阱】\n戰鬥中的攻擊、速度、防守、魔防－４\n在我方的戰鬥中抵銷自己的技能\n（直到敵人下次行動結束）\n\n【混亂】\n戰鬥中的攻擊、速度、防守、魔防下降\n（下降數值為：\n　自己和周圍２格內的我方單位當中最高的弱化值）\n（依能力值不同分開計算）\n\n【弱點暴露】\n受到敵人攻擊時的傷害＋１０"
  },
  {
    "key": "MSID_H_グロア_NOSKW",
    "value": "$a可發動【再移動（格子間的距離，最大３、最少１）】\n容易發動奧義（發動計量－１）\n\n行動後（發動再移動時則於再移動結束後），\n為離自己最近的敵人附加【時間陷阱】的異常狀態，\n離自己最近的敵人與其周圍２格內的敵人速度及魔防－７，\n並附加【混亂】、【弱點暴露】的異常狀態\n（直到敵人下次行動結束）\n\n若現在的回合內自己有進行輔助，\n再移動結束後（包含因再移動限制而結束行動的情況），\n讓自己進入可再次行動的狀態，並可再次發動再移動\n（１回合僅能發動１次，\n　在再移動中受到飛空城陷阱的效果時不會發動）\n\n戰鬥中的攻擊、速度、防守、魔防＋１５，\n給予的傷害＋２５（包括範圍奧義），\n所受傷害－１５（範圍奧義除外），\n且由自己發動攻擊時，\n戰鬥中，若可進行追擊，則會在自己攻擊後立刻追擊"
  },
  {
    "key": "MSID_H_グレイル傭兵団の旗",
    "value": "$a容易發動奧義（發動計量－１）\n\n回合開始時，\n自己和位於自身縱向３列及橫向３列內的我方\n攻擊、防守、魔防的【大器】＋２\n\n若在戰鬥時進行攻擊，戰鬥後，\n自己和位於自身縱向３列及橫向３列內的我方\n攻擊、防守、魔防的【大器】＋４\n\n自己在戰鬥中的攻擊、速度、防守、魔防＋１５，\n抵銷敵人攻擊及防守的＋強化狀態，\n自己給予的傷害＋２５（範圍奧義除外），\n自己所受傷害－１５（範圍奧義除外），\n受到敵人奧義攻擊的傷害再－１５（範圍奧義除外），\n自己在初次追擊前奧義發動計量－２\n\n（受此技能影響的【大器】上限：\n　自己為２０，我方為１０）\n\n【大器】\n依【大器】＋○的數值提升指定能力，\n直到地圖結束\n\n（【大器】的提升值\n　不會超越各技能的上限，\n　提升後的能力值上限為９９。\n　不會被視為有利的狀態）"
  },
  {
    "key": "MSID_H_グレイル傭兵団の旗_NOSKW",
    "value": "$a容易發動奧義（發動計量－１）\n\n回合開始時，\n自己和位於自身縱向３列及橫向３列內的我方\n攻擊、防守、魔防的【大器】＋２\n\n若在戰鬥時進行攻擊，戰鬥後，\n自己和位於自身縱向３列及橫向３列內的我方\n攻擊、防守、魔防的【大器】＋４\n\n自己在戰鬥中的攻擊、速度、防守、魔防＋１５，\n抵銷敵人攻擊及防守的＋強化狀態，\n自己給予的傷害＋２５（範圍奧義除外），\n自己所受傷害－１５（範圍奧義除外），\n受到敵人奧義攻擊的傷害再－１５（範圍奧義除外），\n自己在初次追擊前奧義發動計量－２\n\n（受此技能影響的【大器】上限：\n　自己為２０，我方為１０）"
  },
  {
    "key": "MSID_H_教え導く師の槍",
    "value": "$a容易發動奧義（發動計量－１）\n受到敵人攻擊時，可無視距離進行反擊\n\n回合開始時，\n自己和位於自身縱向３列及橫向３列內的我方\n攻擊及速度的【大器】＋２\n\n若在戰鬥時進行攻擊，戰鬥後，\n自己和位於自身縱向３列及橫向３列內的我方\n攻擊及速度的【大器】＋４\n\n戰鬥中的攻擊、速度、防守、魔防＋１５，\n給予的傷害＋２５（範圍奧義除外），\n所受傷害－１５（範圍奧義除外），\n受到敵人奧義攻擊的傷害再－１５（範圍奧義除外），\n抵銷自己的奧義發動計量變化量－\n\n可使用下述的【戰法】\n―――――――【戰法】：霸天―――――――\n可攻擊與自己相距３格的敵人（無法攻擊相鄰的敵人）\n\n戰鬥中，自己在初次攻擊前奧義發動計量－１，\n發動奧義時，若敵人為龍、獸，\n造成的傷害＋（攻擊×２０％）（範圍奧義除外）\n\n敵人發動【防護屏障】效果時，無法穿越\n其周圍３格以內的格子（若持有穿越則無效）\n滿足下列任一條件時，將受到反擊\n（條件Ａ：敵人為射程為１格的重裝時\n　條件Ｂ：敵人擁有「可無視距離進行反擊」時）\n戰鬥後移動技能會無效\n技能效果的射程判定視為射程為１\n使用戰法後，２回合內無法使用\n―――――――――――――――――――――\n（受此技能影響的【大器】上限：\n　自己為２０，我方為１０）\n\n【大器】\n依【大器】＋○的數值提升指定能力，\n直到地圖結束\n\n（【大器】的提升值\n　不會超越各技能的上限，\n　提升後的能力值上限為９９。\n　不會被視為有利的狀態）\n\n【戰法】\n點觸畫面下方的「戰法按鈕」，即可使用戰法\n\n戰法狀態僅在技能持有者行動時有效\n若自身處於雙人組合狀態，\n或裝備多個持有戰法的技能，\n戰法將無效"
  },
  {
    "key": "MSID_H_教え導く師の槍_NOSKW",
    "value": "$a容易發動奧義（發動計量－１）\n受到敵人攻擊時，可無視距離進行反擊\n\n回合開始時，\n自己和位於自身縱向３列及橫向３列內的我方\n攻擊及速度的【大器】＋２\n\n若在戰鬥時進行攻擊，戰鬥後，\n自己和位於自身縱向３列及橫向３列內的我方\n攻擊及速度的【大器】＋４\n\n戰鬥中的攻擊、速度、防守、魔防＋１５，\n給予的傷害＋２５（範圍奧義除外），\n所受傷害－１５（範圍奧義除外），\n受到敵人奧義攻擊的傷害再－１５（範圍奧義除外），\n抵銷自己的奧義發動計量變化量－\n\n可使用下述的【戰法】\n―――――――【戰法】：霸天―――――――\n可攻擊與自己相距３格的敵人（無法攻擊相鄰的敵人）\n\n戰鬥中，自己在初次攻擊前奧義發動計量－１，\n發動奧義時，若敵人為龍、獸，\n造成的傷害＋（攻擊×２０％）（範圍奧義除外）\n\n敵人發動【防護屏障】效果時，無法穿越\n其周圍３格以內的格子（若持有穿越則無效）\n滿足下列任一條件時，將受到反擊\n（條件Ａ：敵人為射程為１格的重裝時\n　條件Ｂ：敵人擁有「可無視距離進行反擊」時）\n戰鬥後移動技能會無效\n技能效果的射程判定視為射程為１\n使用戰法後，２回合內無法使用\n―――――――――――――――――――――\n（受此技能影響的【大器】上限：\n　自己為２０，我方為１０）"
  },
  {
    "key": "MSID_H_物陰からのバトン",
    "value": "$a容易發動奧義（發動計量－１）\n\n自己和周圍３格內的我方\n以及地圖上被賦予【赤紅詛咒】的我方\n戰鬥中的攻擊、速度、防守、魔防＋○\n（○的數值為：自己為１５，我方為５），\n抵銷敵人的＋強化狀態，\n自己在初次攻擊前奧義發動計量－\n持有此技能者以外，地圖上\n被賦予【赤紅詛咒】的我方人數\n（自己最大３，我方最大２）\n（即使條件重複，效果也不會重複）\n\n戰鬥中的攻擊＋（奧義發動計量最大值×４），\n所受傷害－１５（範圍奧義除外），\n抵銷敵人擁有的絕對追擊狀態，\n以及自己受到的無法追擊狀態，\n且在追擊的速度條件－１０的狀態下\n滿足追擊的速度條件時\n（不包含絕對追擊、無法追擊），\n戰鬥中發動【神速追擊：傷害１００％】\n\n【赤紅詛咒】\n周圍３格內的敵人戰鬥中的速度、防守、魔防－４\n\n【神速追擊：傷害１００％】\n於自己的一般追擊後，立刻發動額外追擊\n透過神速追擊給予的傷害為一般攻擊時的１００％\n（自己無法追擊時，將於一般追擊的時間點發動）\n（神速追擊將被視為追擊，\n　會受「傷害降低◯◯％」等效果影響，\n　但不受無法追擊、攻擊２次的效果影響）\n（若有多個相同系統效果，僅取最大值）"
  },
  {
    "key": "MSID_H_物陰からのバトン_NOSKW",
    "value": "$a容易發動奧義（發動計量－１）\n\n自己和周圍３格內的我方\n以及地圖上被賦予【赤紅詛咒】的我方\n戰鬥中的攻擊、速度、防守、魔防＋○\n（○的數值為：自己為１５，我方為５），\n抵銷敵人的＋強化狀態，\n自己在初次攻擊前奧義發動計量－\n持有此技能者以外，地圖上\n被賦予【赤紅詛咒】的我方人數\n（自己最大３，我方最大２）\n（即使條件重複，效果也不會重複）\n\n戰鬥中的攻擊＋（奧義發動計量最大值×４），\n所受傷害－１５（範圍奧義除外），\n抵銷敵人擁有的絕對追擊狀態，\n以及自己受到的無法追擊狀態，\n且在追擊的速度條件－１０的狀態下\n滿足追擊的速度條件時\n（不包含絕對追擊、無法追擊），\n戰鬥中發動【神速追擊：傷害１００％】"
  },
  {
    "key": "MSID_H_運動する体の角",
    "value": "$a可發動【再移動（格子間的距離＋１，最大４）】\n容易發動奧義（發動計量－１）\n\n我軍回合及敵軍回合開始時，\n自己和周圍２格內的我方單位攻擊及防守＋６，\n並賦予【狀態奪取無效】、【識破・慌亂】的效果\n（１回合）\n\n發動回合開始技能後，\n以及發動飛空城防衛時的敵軍第１回合開始技能後，\n自己和周圍２格內的我方\n若攻擊、速度、防守、魔防受到強化，\n則賦予其所受到的各能力強化＋３的值\n（１回合，依能力值不同分開計算，上限１０）\n\n戰鬥中的攻擊、防守、魔防＋１６，\n給予的傷害＋○（範圍奧義除外），\n所受傷害－○的５０％（範圍奧義除外），\n受到敵人奧義攻擊的傷害再－○的５０％（範圍奧義除外）\n（○的數值為：自己和位於自身縱向３列及橫向３列內的\n　我方單位當中，強化狀態合計值的最高值），\n使敵人奧義相關技能以外的\n「傷害降低◯◯％」效果減少一半\n（計算效果時，小數點後無條件捨去）（範圍奧義除外）\n\n回合開始時，若未與龍、獸以外的我方相鄰則為化身狀態\n（若非上述情形，將解除化身狀態）\n處於化身狀態時，攻擊＋２，\n且戰鬥中，敵人的攻擊及防守下降\n（下降數值為：\n　攻擊方移動前與移動後的格子距離（最大３）＋３），\n且移動前與移動後的格子距離若為２以上，\n將自己在戰鬥中受到的第一發攻擊傷害降低３０％\n\n【再移動（格子間的距離＋１，最大４）】\n由自己發動攻擊、輔助及破壞地形的行動後，\n可馬上移動\n\n可移動的範圍為\n上述行動前的移動前與移動後的格子距離＋１\n（最大４）\n\n【狀態奪取無效】\n戰鬥中的攻擊、速度、防守、魔防＋４\n\n對受到此狀態者，\n發動【奪取埃基璐】等技能的\n「賦予敵人受到的【有利的狀態】」以及\n「解除敵人的【有利的狀態】」的效果時，\n抵銷自己和其他目標的該效果，\n並解除敵人的【有利的狀態】\n（無法解除敵人於同一時間賦予的【有利的狀態】）\n\n【識破・慌亂】\n被附加「慌亂」\n（強化狀態由＋轉－的異常狀態）時，\n抵銷其「強化狀態由＋轉－」的效果\n（１回合）\n\n【有利的狀態】\n「１回合」的所有效果\n（強化、移動＋１、敵人弱化傷害＋等）"
  },
  {
    "key": "MSID_H_運動する体の角_NOSKW",
    "value": "$a可發動【再移動（格子間的距離＋１，最大４）】\n容易發動奧義（發動計量－１）\n\n我軍回合及敵軍回合開始時，\n自己和周圍２格內的我方單位攻擊及防守＋６，\n並賦予【狀態奪取無效】、【識破・慌亂】的效果\n（１回合）\n\n發動回合開始技能後，\n以及發動飛空城防衛時的敵軍第１回合開始技能後，\n自己和周圍２格內的我方\n若攻擊、速度、防守、魔防受到強化，\n則賦予其所受到的各能力強化＋３的值\n（１回合，依能力值不同分開計算，上限１０）\n\n戰鬥中的攻擊、防守、魔防＋１６，\n給予的傷害＋○（範圍奧義除外），\n所受傷害－○的５０％（範圍奧義除外），\n受到敵人奧義攻擊的傷害再－○的５０％（範圍奧義除外）\n（○的數值為：自己和位於自身縱向３列及橫向３列內的\n　我方單位當中，強化狀態合計值的最高值），\n使敵人奧義相關技能以外的\n「傷害降低◯◯％」效果減少一半\n（計算效果時，小數點後無條件捨去）（範圍奧義除外）\n\n回合開始時，若未與龍、獸以外的我方相鄰則為化身狀態\n（若非上述情形，將解除化身狀態）\n處於化身狀態時，攻擊＋２，\n且戰鬥中，敵人的攻擊及防守下降\n（下降數值為：\n　攻擊方移動前與移動後的格子距離（最大３）＋３），\n且移動前與移動後的格子距離若為２以上，\n將自己在戰鬥中受到的第一發攻擊傷害降低３０％"
  },
  {
    "key": "MSID_H_真天刻の拍動",
    "value": "$a發動奧義時，增加速度數值的奧義傷害\n\n回合開始時，以及英雄決鬥以外的敵軍回合開始時，\n賦予自己和周圍３格內的我方\n【老師的引導・技能】、【迴避】的效果（１回合），\n自己和周圍３格內的我方，\n若各自的奧義發動計量為最大值，奧義發動計量－１\n\n受到敵人攻擊時，\n戰鬥中，若自己的速度高於敵人，可搶先攻擊\n\n將戰鬥中一開始受到的攻擊和攻擊２次的傷害降低○％\n（○的數值為：由自己發動攻擊時\n　及在各回合中，持有此技能者\n　受到敵人攻擊的初次戰鬥時為８０，\n　若非上述情形時則為４０），\n受到的追擊傷害降低４０％，\n且在追擊的速度條件－１０的狀態下\n滿足追擊的速度條件時\n（不包含絕對追擊、無法追擊），\n戰鬥中發動【神速追擊：傷害１００％】\n\n【老師的引導・技能】\n存活時，可透過戰鬥或輔助取得２倍ＳＰ\n（若有多個相同系統效果，僅取最大值）\n\n戰鬥中的攻擊、速度、防守、魔防＋５，\n給予的傷害＋７（範圍奧義除外），\n所受傷害－７（範圍奧義除外），\n戰鬥後，奧義發動計量－１\n\n【迴避】\n速度高於敵人時，受到的範圍奧義傷害\n以及戰鬥中所受到的攻擊傷害\n降低速度差×４％（最大４０％）\n（巨影的範圍奧義除外）\n\n【神速追擊：傷害１００％】\n於自己的一般追擊後，立刻發動額外追擊\n透過神速追擊給予的傷害為一般攻擊時的１００％\n（自己無法追擊時，將於一般追擊的時間點發動）\n（神速追擊將被視為追擊，\n　會受「傷害降低◯◯％」等效果影響，\n　但不受無法追擊、攻擊２次的效果影響）\n（若有多個相同系統效果，僅取最大值）"
  },
  {
    "key": "MSID_H_真天刻の拍動_NOSKW",
    "value": "$a發動奧義時，增加速度數值的奧義傷害\n\n回合開始時，以及英雄決鬥以外的敵軍回合開始時，\n賦予自己和周圍３格內的我方\n【老師的引導・技能】、【迴避】的效果（１回合），\n自己和周圍３格內的我方，\n若各自的奧義發動計量為最大值，奧義發動計量－１\n\n受到敵人攻擊時，\n戰鬥中，若自己的速度高於敵人，可搶先攻擊\n\n將戰鬥中一開始受到的攻擊和攻擊２次的傷害降低○％\n（○的數值為：由自己發動攻擊時\n　及在各回合中，持有此技能者\n　受到敵人攻擊的初次戰鬥時為８０，\n　若非上述情形時則為４０），\n受到的追擊傷害降低４０％，\n且在追擊的速度條件－１０的狀態下\n滿足追擊的速度條件時\n（不包含絕對追擊、無法追擊），\n戰鬥中發動【神速追擊：傷害１００％】"
  },
  {
    "key": "MSID_H_正真蒼炎の天空",
    "value": "$a發動奧義時，\n增加自己及敵人的防守中較高方的數值的奧義傷害，\n回復自身最高ＨＰ的５０％\n\n我軍回合及敵軍回合開始時，\n賦予自己和周圍２格內的我方\n【蒼炎勇者】、\n「戰鬥中使敵人奧義相關技能以外的\n　『傷害降低◯◯％』效果減少一半\n　（計算效果時，小數點後無條件捨去）\n　（範圍奧義除外）」的效果（１回合）\n\n若敵人可進行追擊，\n則敵人會在攻擊後立刻進行追擊\n\n戰鬥中抵銷自己的奧義發動計量變化量－，\n抵銷【無法回復】的５０％效果，抵銷無法反擊狀態，\n受到的攻擊傷害降低４０％，\n但受到連續攻擊時，\n第二次攻擊以後的傷害降低７０％\n（範圍奧義除外）\n\n【蒼炎勇者】\n受到敵人攻擊時，可無視距離進行反擊\n\n戰鬥中的攻擊、速度、防守、魔防＋５，\n將戰鬥中一開始受到的攻擊和攻擊２次的傷害－１０，\n且發動奧義時，\n造成的傷害＋（奧義發動計量最大值×４）\n（範圍奧義除外）\n\n【無法回復】\n無法回復ＨＰ的異常狀態\n（直到敵人下次行動結束）"
  },
  {
    "key": "MSID_H_正真蒼炎の天空_NOSKW",
    "value": "$a發動奧義時，\n增加自己及敵人的防守中較高方的數值的奧義傷害，\n回復自身最高ＨＰ的５０％\n\n我軍回合及敵軍回合開始時，\n賦予自己和周圍２格內的我方\n【蒼炎勇者】、\n「戰鬥中使敵人奧義相關技能以外的\n　『傷害降低◯◯％』效果減少一半\n　（計算效果時，小數點後無條件捨去）\n　（範圍奧義除外）」的效果（１回合）\n\n若敵人可進行追擊，\n則敵人會在攻擊後立刻進行追擊\n\n戰鬥中抵銷自己的奧義發動計量變化量－，\n抵銷【無法回復】的５０％效果，抵銷無法反擊狀態，\n受到的攻擊傷害降低４０％，\n但受到連續攻擊時，\n第二次攻擊以後的傷害降低７０％\n（範圍奧義除外）"
  },
  {
    "key": "MSID_H_真肉体の咆哮",
    "value": "發動奧義時，增加防守數值的奧義傷害\n\n自己和位於自身縱向３列及橫向３列內的我方，\n戰鬥中的攻擊、速度、防守、魔防＋○\n（○的數值為：自己和地圖上的我方單位當中\n　最高的強化值（依能力值不同分開計算）），\n自己在初次攻擊前奧義發動計量－◇\n（◇的數值為：\n　自己：自己和地圖上的我方單位當中\n　　　　強化狀態合計值的最高值÷１２\n　我方：自己和地圖上的我方單位當中\n　　　　強化狀態合計值的最高值÷１８\n　（小數點後無條件捨去））\n\n戰鬥開始時的攻擊為（敵人的攻擊－５）以上時，\n戰鬥中，敵人的攻擊及防守－７\n\n戰鬥開始時的防守為（敵人的防守－５）以上時，\n戰鬥中，敵人的攻擊及防守－７\n\n將戰鬥中受到的攻擊傷害降低４０％\n（範圍奧義除外），必定可進行追擊"
  },
  {
    "key": "MSID_H_真あの世行きよ…",
    "value": "$a攻擊、速度、防守、魔防＋９\n\n我軍回合及敵軍回合開始時，\n賦予自己和周圍３格內的我方\n【赤紅詛咒】、【追擊之躍動】、【真突擊】的效果\n（１回合）\n\n戰鬥中給予的傷害＋○×３（範圍奧義除外），\n受到的攻擊傷害降低○×２０％\n（範圍奧義除外），\n所受傷害再－○×３\n（範圍奧義除外），\n且○為２以上時，\n戰鬥中，敵人無法發動奧義\n（範圍奧義除外）\n\n戰鬥後回復ＨＰ\n（回復數值為：○×３）\n\n（○的數值為：地圖上被賦予【赤紅詛咒】的\n　我方人數（自己除外），最大３）\n\n【赤紅詛咒】\n周圍３格內的敵人戰鬥中的速度、防守、魔防－４\n\n【追擊之躍動】\n戰鬥中，自己在初次追擊前奧義發動計量－２\n\n【真突擊】\n可移動至自己十字方向３格以內的格子\n透過此效果進行移動時\n不受技能的妨礙移動效果影響\n（無法越過敵人或無法移動的地形進行移動）\n（將被視為傳送）"
  },
  {
    "key": "MSID_H_真あの世行きよ…_NOSKW",
    "value": "$a攻擊、速度、防守、魔防＋９\n\n我軍回合及敵軍回合開始時，\n賦予自己和周圍３格內的我方\n【赤紅詛咒】、【追擊之躍動】、【真突擊】的效果\n（１回合）\n\n戰鬥中給予的傷害＋○×３（範圍奧義除外），\n受到的攻擊傷害降低○×２０％\n（範圍奧義除外），\n所受傷害再－○×３\n（範圍奧義除外），\n且○為２以上時，\n戰鬥中，敵人無法發動奧義\n（範圍奧義除外）\n\n戰鬥後回復ＨＰ\n（回復數值為：○×３）\n\n（○的數值為：地圖上被賦予【赤紅詛咒】的\n　我方人數（自己除外），最大３）"
  },
  {
    "key": "MSID_H_合気・強化無効",
    "value": "若有會將速度差距列入條件的技能，\n則將自身的速度＋７後再進行比較\n\n受到的範圍奧義傷害降低８０％\n（巨影的範圍奧義除外）\n\n戰鬥中，敵人的攻擊、速度、防守－４，\n抵銷敵人的＋強化狀態\n自己給予的傷害＋（速度×２０％）（範圍奧義除外），\n自己所受傷害－（速度×２０％）（範圍奧義除外），\n抵銷無法反擊狀態"
  },
  {
    "key": "MSID_H_追撃の鼓動・術策",
    "value": "$a我軍回合及敵軍回合開始時，\n為位於自身縱向３列及橫向３列內\n魔防低於（自己的魔防＋５）的敵人\n附加【弱點暴露】、【不和】的異常狀態\n（直到敵人下次行動結束）\n\n戰鬥中的攻擊及速度提升\n（提升數值為：奧義發動計量的最大值＋２），\n將戰鬥中一開始受到的攻擊和攻擊２次的傷害－５，\n自己在初次追擊前奧義發動計量－２\n\n【弱點暴露】\n受到敵人攻擊時的傷害＋１０\n\n【不和】\n戰鬥中的攻擊、速度、防守、魔防下降\n（下降數值為：周圍２格內的我方人數（上限３）＋２）"
  },
  {
    "key": "MSID_H_追撃の鼓動・術策_NOSKW",
    "value": "$a我軍回合及敵軍回合開始時，\n為位於自身縱向３列及橫向３列內\n魔防低於（自己的魔防＋５）的敵人\n附加【弱點暴露】、【不和】的異常狀態\n（直到敵人下次行動結束）\n\n戰鬥中的攻擊及速度提升\n（提升數值為：奧義發動計量的最大值＋２），\n將戰鬥中一開始受到的攻擊和攻擊２次的傷害－５，\n自己在初次追擊前奧義發動計量－２"
  },
  {
    "key": "MSID_H_攻速信念・弱化無効",
    "value": "$a我軍回合及敵軍回合開始時，\n賦予自己【防護屏障】的效果（１回合），\n自己和周圍２格內的我方單位\n攻擊及速度＋６，\n並賦予「抵銷弱化狀態」的效果（１回合）\n\n戰鬥中的攻擊及速度提升\n（提升數值為：位於自身縱向３列及橫向３列內的\n　我方人數×２）（最大６），\n給予的傷害＋５（範圍奧義除外），\n將戰鬥中一開始受到的攻擊和攻擊２次的傷害－５\n\n【防護屏障】\n讓攻擊射程為１格的敵人無法穿越\n自己周圍１格以內的格子（對持有穿越的敵人無效）\n讓攻擊射程為２格的敵人無法穿越\n自己周圍２格以內的格子（對持有穿越的敵人無效）"
  },
  {
    "key": "MSID_H_攻速信念・弱化無効_NOSKW",
    "value": "$a我軍回合及敵軍回合開始時，\n賦予自己【防護屏障】的效果（１回合），\n自己和周圍２格內的我方單位\n攻擊及速度＋６，\n並賦予「抵銷弱化狀態」的效果（１回合）\n\n戰鬥中的攻擊及速度提升\n（提升數值為：位於自身縱向３列及橫向３列內的\n　我方人數×２）（最大６），\n給予的傷害＋５（範圍奧義除外），\n將戰鬥中一開始受到的攻擊和攻擊２次的傷害－５"
  },
  {
    "key": "MSID_H_守魔信念・弱化無効",
    "value": "$a我軍回合及敵軍回合開始時，\n賦予自己【防護屏障】的效果（１回合），\n自己和周圍２格內的我方單位\n防守及魔防＋６，\n並賦予「抵銷弱化狀態」的效果（１回合）\n\n戰鬥中的防守及魔防提升\n（提升數值為：位於自身縱向３列及橫向３列內的\n　我方人數×２）（最大６），\n給予的傷害＋５（範圍奧義除外），\n將戰鬥中一開始受到的攻擊和攻擊２次的傷害－５\n\n【防護屏障】\n讓攻擊射程為１格的敵人無法穿越\n自己周圍１格以內的格子（對持有穿越的敵人無效）\n讓攻擊射程為２格的敵人無法穿越\n自己周圍２格以內的格子（對持有穿越的敵人無效）"
  },
  {
    "key": "MSID_H_守魔信念・弱化無効_NOSKW",
    "value": "$a我軍回合及敵軍回合開始時，\n賦予自己【防護屏障】的效果（１回合），\n自己和周圍２格內的我方單位\n防守及魔防＋６，\n並賦予「抵銷弱化狀態」的效果（１回合）\n\n戰鬥中的防守及魔防提升\n（提升數值為：位於自身縱向３列及橫向３列內的\n　我方人數×２）（最大６），\n給予的傷害＋５（範圍奧義除外），\n將戰鬥中一開始受到的攻擊和攻擊２次的傷害－５"
  },
  {
    "key": "MSID_H_双界ベレス",
    "value": "$a賦予與自己相同出處的我方及自己本身\n【雙界效果・刃】、【雙界效果・盾】的狀態\n\n賦予自己的格子和周圍３格內的格子\n【天脈・深綠】的效果（２回合）\n\n【雙界效果・刃】\n戰鬥中的攻擊及速度＋４（１回合）\n\n【雙界效果・盾】\n戰鬥中的防守及魔防＋４\n僅分別在我軍與敵軍的各回合當中，\n自身於初次戰鬥時，敵方無法追擊\n（１回合）\n\n【天脈・深綠】\n進入被賦予此效果的格子中的對象會受到以下效果\n\n敵人無法透過技能效果從此格子傳送\n或傳送到此格子\n（對持有穿越的敵人無效）\n（可透過壓制戰的據點等其他地形的效果傳送）\n\n為在此格子中發動再移動的敵人\n附加【再移動限制】的異常狀態（直到敵人下次行動結束）\n\n敵人在戰鬥中的攻擊及速度－５，\n奧義發動計量變化量－１\n（若有多個相同系統效果，僅取最大值），\n且若裝備有在攻擊時發動的奧義，\n戰鬥中，在初次攻擊前奧義發動計量＋１\n（奧義發動計量不會超越最大值）\n\n（若賦予的格子上已有天脈效果，將會取代該效果）\n（若在同一時間賦予多個不同的天脈效果，\n　天脈效果將會消滅）\n\n【再移動限制】\n受到此異常狀態的敵人攻擊射程為１格時，\n發動再移動後可馬上移動的範圍限為最大１格\n敵人攻擊射程為２格時，會在發動再移動後立刻結束行動"
  },
  {
    "key": "MSID_H_双界ベレス_NOSKW",
    "value": "$a賦予與自己相同出處的我方及自己本身\n【雙界效果・刃】、【雙界效果・盾】的狀態\n\n賦予自己的格子和周圍３格內的格子\n【天脈・深綠】的效果（２回合）"
  },
  {
    "key": "MSID_H_至光アーリアル改",
    "value": "克制魔法\n容易發動奧義（發動計量－１）\n\n戰鬥中的攻擊、速度、防守、魔防＋５，\n給予的傷害＋２５（範圍奧義除外），\n所受傷害－１５（範圍奧義除外），\n敵人奧義發動計量變化量－１\n（若有多個相同系統效果，僅取最大值），\n且抵銷敵人的「以其防守及魔防中較低方計算傷害」效果\n（包括範圍奧義）"
  },
  {
    "key": "MSID_H_ヘイズ改",
    "value": "$a容易發動奧義（發動計量－１）\n\n使用或被施放支援、移動系輔助技能時，\n移動後，自己和對方各自\n縱向３列及橫向３列內的敵人\n攻擊、速度、防守、魔防－６，\n並附加【取消】、【混亂】、【速度枷鎖】的異常狀態\n（直到敵人下次行動結束）\n\n戰鬥中的攻擊、速度、防守、魔防＋５，\n給予的傷害＋２５（範圍奧義除外），\n受到的攻擊傷害降低４０％\n（範圍奧義除外），\n所受傷害再－７（範圍奧義除外）\n\n【取消】\n使奧義發動計量變化量－１的異常狀態\n（若有多個相同系統效果，僅取最大值）\n\n【混亂】\n戰鬥中的攻擊、速度、防守、魔防下降\n（下降數值為：\n　自己和周圍２格內的我方單位當中最高的弱化值）\n（依能力值不同分開計算）\n\n【速度枷鎖】\n戰鬥中的速度下降\n（下降數值為：自己受到的弱化以外\n　【不利的異常狀態】數量＋４）（最大８）"
  },
  {
    "key": "MSID_H_ヘイズ改_NOSKW",
    "value": "$a容易發動奧義（發動計量－１）\n\n使用或被施放支援、移動系輔助技能時，\n移動後，自己和對方各自\n縱向３列及橫向３列內的敵人\n攻擊、速度、防守、魔防－６，\n並附加【取消】、【混亂】、【速度枷鎖】的異常狀態\n（直到敵人下次行動結束）\n\n戰鬥中的攻擊、速度、防守、魔防＋５，\n給予的傷害＋２５（範圍奧義除外），\n受到的攻擊傷害降低４０％\n（範圍奧義除外），\n所受傷害再－７（範圍奧義除外）"
  },
  {
    "key": "MSID_H_透き通る玻璃の弓改",
    "value": "$a可發動【再移動（２）】\n克制飛行　攻擊＋３\n\n戰鬥中的攻擊及速度＋６、防守及魔防＋５，\n給予的傷害＋２０（包括範圍奧義），\n所受傷害－７（範圍奧義除外），\n且由自己發動攻擊時，\n戰鬥中，若可進行追擊，則會在自己攻擊後立刻追擊\n\n【再移動（２）】\n由自己發動攻擊、輔助及破壞地形的行動後，\n馬上可進行２格以內的移動\n（若有多個相同系統效果，僅取最大值）\n（１回合僅能發動１次）"
  },
  {
    "key": "MSID_H_透き通る玻璃の弓改_NOSKW",
    "value": "$a可發動【再移動（２）】\n克制飛行　攻擊＋３\n\n戰鬥中的攻擊及速度＋６、防守及魔防＋５，\n給予的傷害＋２０（包括範圍奧義），\n所受傷害－７（範圍奧義除外），\n且由自己發動攻擊時，\n戰鬥中，若可進行追擊，則會在自己攻擊後立刻追擊"
  },
  {
    "key": "MSID_H_ジャハナ王の砂刃改",
    "value": "$a容易發動奧義（發動計量－１）\n\n自己在戰鬥中的攻擊及速度＋６、防守及魔防＋５，\n抵銷敵人速度及防守的強化狀態，\n自己所受傷害－７（範圍奧義除外），\n抵銷自己的奧義發動計量變化量－\n\n戰鬥對手位於自己十字方向上時，\n戰鬥中，敵人無法反擊，\n抵銷來自戰鬥對手以外的敵軍技能\n\n戰鬥對手不位於自己十字方向上時，\n戰鬥中造成的傷害＋（敵人的攻擊×２０％）\n（包括範圍奧義），\n奧義相關技能以外的\n「傷害降低◯◯％」效果減少一半\n（計算效果時，小數點後無條件捨去）（範圍奧義除外）\n\n【暗器（７）】效果\n\n【暗器（７）】\n若在戰鬥時進行攻擊，戰鬥後，\n對方與其周圍２格內的敵人防守及魔防－７\n（直到敵人下次行動結束）"
  },
  {
    "key": "MSID_H_ジャハナ王の砂刃改_NOSKW",
    "value": "$a容易發動奧義（發動計量－１）\n\n自己在戰鬥中的攻擊及速度＋６、防守及魔防＋５，\n抵銷敵人速度及防守的強化狀態，\n自己所受傷害－７（範圍奧義除外），\n抵銷自己的奧義發動計量變化量－\n\n戰鬥對手位於自己十字方向上時，\n戰鬥中，敵人無法反擊，\n抵銷來自戰鬥對手以外的敵軍技能\n\n戰鬥對手不位於自己十字方向上時，\n戰鬥中造成的傷害＋（敵人的攻擊×２０％）\n（包括範圍奧義），\n奧義相關技能以外的\n「傷害降低◯◯％」效果減少一半\n（計算效果時，小數點後無條件捨去）（範圍奧義除外）\n\n【暗器（７）】效果"
  },
  {
    "key": "MSID_H_雇われ魔道士の書改",
    "value": "速度＋３\n\n戰鬥中的攻擊、速度、防守、魔防\n會根據自己使用神龍之花的次數提升，\n最大＋１２\n（使用次數為５次以上時＋１２、\n　４次時＋１１、３次時＋１０、２次以下時＋９），\n抵銷敵人擁有的絕對追擊狀態，\n以及自己受到的無法追擊狀態，\n所受傷害－７（範圍奧義除外）\n\n若自己使用神龍之花的次數為３次以上，\n戰鬥中的攻擊、速度、防守、魔防再提升\n（提升數值為：\n　自己和地圖上的我方單位當中\n　最高的強化值）（依能力值不同分開計算）"
  },
  {
    "key": "MID_CHAPTER_TITLE_CX125",
    "value": "外傳１２６"
  },
  {
    "key": "MID_CHAPTER_CX125",
    "value": "兩人的運動祭"
  },
  {
    "key": "MID_STAGE_TITLE_X1251",
    "value": "外傳１２６—１節"
  },
  {
    "key": "MID_STAGE_TITLE_X1252",
    "value": "外傳１２６—２節"
  },
  {
    "key": "MID_STAGE_TITLE_X1253",
    "value": "外傳１２６—３節"
  },
  {
    "key": "MID_STAGE_X1251",
    "value": "臨時參加"
  },
  {
    "key": "MID_STAGE_X1252",
    "value": "愛的力量"
  },
  {
    "key": "MID_STAGE_X1253",
    "value": "下次要做什麼"
  },
  {
    "key": "MID_STAGE_TITLE_SB_0108",
    "value": "第１０８迷宮"
  },
  {
    "key": "MID_CHAPTER_ST_CX063",
    "value": "外傳１２５～１２６"
  },
  {
    "key": "MID_STAGE_TITLE_ST_X0124",
    "value": "外傳１２５"
  },
  {
    "key": "MID_STAGE_TITLE_ST_X0125",
    "value": "外傳１２６"
  },
  {
    "key": "MID_STAGE_TITLE_ST_X1125",
    "value": "外傳１２５～１２６"
  },
  {
    "key": "MID_STAGE_TITLE_PB319",
    "value": "技能篇３１９"
  },
  {
    "key": "MID_STAGE_PB319",
    "value": "送上聲援的教師與啦啦隊員"
  }
]
