[
  {
    "hero_id": "PID_伝承ギネヴィア",
    "active": {
      "start": "2024-08-20T07:00:00Z",
      "finish": "2024-08-27T07:00:00Z",
      "_skip0": null
    },
    "_skip0": null
  },
  {
    "hero_id": "PID_双界ネフェニー",
    "active": {
      "start": "2024-08-20T07:00:00Z",
      "finish": "2024-08-27T07:00:00Z",
      "_skip0": null
    },
    "_skip0": null
  },
  {
    "hero_id": "PID_浴衣ワユ",
    "active": {
      "start": "2024-08-20T07:00:00Z",
      "finish": "2024-08-27T07:00:00Z",
      "_skip0": null
    },
    "_skip0": null
  },
  {
    "hero_id": "PID_浴衣ルキノ",
    "active": {
      "start": "2024-08-20T07:00:00Z",
      "finish": "2024-08-27T07:00:00Z",
      "_skip0": null
    },
    "_skip0": null
  },
  {
    "hero_id": "PID_浴衣レオン",
    "active": {
      "start": "2024-08-20T07:00:00Z",
      "finish": "2024-08-27T07:00:00Z",
      "_skip0": null
    },
    "_skip0": null
  },
  {
    "hero_id": "PID_浴衣タクミ",
    "active": {
      "start": "2024-08-20T07:00:00Z",
      "finish": "2024-08-27T07:00:00Z",
      "_skip0": null
    },
    "_skip0": null
  },
  {
    "hero_id": "PID_催眠デューテ",
    "active": {
      "start": "2024-08-20T07:00:00Z",
      "finish": "2024-08-27T07:00:00Z",
      "_skip0": null
    },
    "_skip0": null
  },
  {
    "hero_id": "PID_ガトリー",
    "active": {
      "start": "2024-08-20T07:00:00Z",
      "finish": "2024-08-27T07:00:00Z",
      "_skip0": null
    },
    "_skip0": null
  },
  {
    "hero_id": "PID_ユリア",
    "active": {
      "start": "2024-08-20T07:00:00Z",
      "finish": "2024-08-27T07:00:00Z",
      "_skip0": null
    },
    "_skip0": null
  },
  {
    "hero_id": "PID_アルフォンス",
    "active": {
      "start": "2024-08-20T07:00:00Z",
      "finish": "2024-08-27T07:00:00Z",
      "_skip0": null
    },
    "_skip0": null
  },
  {
    "hero_id": "PID_伝承カミラ",
    "active": {
      "start": "2024-08-27T07:00:00Z",
      "finish": "2024-09-03T07:00:00Z",
      "_skip0": null
    },
    "_skip0": null
  },
  {
    "hero_id": "PID_双界ネフェニー",
    "active": {
      "start": "2024-08-27T07:00:00Z",
      "finish": "2024-09-03T07:00:00Z",
      "_skip0": null
    },
    "_skip0": null
  },
  {
    "hero_id": "PID_浴衣ワユ",
    "active": {
      "start": "2024-08-27T07:00:00Z",
      "finish": "2024-09-03T07:00:00Z",
      "_skip0": null
    },
    "_skip0": null
  },
  {
    "hero_id": "PID_浴衣ルキノ",
    "active": {
      "start": "2024-08-27T07:00:00Z",
      "finish": "2024-09-03T07:00:00Z",
      "_skip0": null
    },
    "_skip0": null
  },
  {
    "hero_id": "PID_浴衣レオン",
    "active": {
      "start": "2024-08-27T07:00:00Z",
      "finish": "2024-09-03T07:00:00Z",
      "_skip0": null
    },
    "_skip0": null
  },
  {
    "hero_id": "PID_浴衣タクミ",
    "active": {
      "start": "2024-08-27T07:00:00Z",
      "finish": "2024-09-03T07:00:00Z",
      "_skip0": null
    },
    "_skip0": null
  },
  {
    "hero_id": "PID_シンシア",
    "active": {
      "start": "2024-08-27T07:00:00Z",
      "finish": "2024-09-03T07:00:00Z",
      "_skip0": null
    },
    "_skip0": null
  },
  {
    "hero_id": "PID_セテス",
    "active": {
      "start": "2024-08-27T07:00:00Z",
      "finish": "2024-09-03T07:00:00Z",
      "_skip0": null
    },
    "_skip0": null
  },
  {
    "hero_id": "PID_アイク",
    "active": {
      "start": "2024-08-27T07:00:00Z",
      "finish": "2024-09-03T07:00:00Z",
      "_skip0": null
    },
    "_skip0": null
  }
]
