[
  {
    "hero_id": "PID_伝承シェズ男",
    "active": {
      "start": "2024-09-10T07:00:00Z",
      "finish": "2024-09-17T07:00:00Z",
      "_skip0": null
    },
    "_skip0": null
  },
  {
    "hero_id": "PID_総選挙アルフォンス",
    "active": {
      "start": "2024-09-10T07:00:00Z",
      "finish": "2024-09-17T07:00:00Z",
      "_skip0": null
    },
    "_skip0": null
  },
  {
    "hero_id": "PID_総選挙フェリクス",
    "active": {
      "start": "2024-09-10T07:00:00Z",
      "finish": "2024-09-17T07:00:00Z",
      "_skip0": null
    },
    "_skip0": null
  },
  {
    "hero_id": "PID_総選挙ベルナデッタ",
    "active": {
      "start": "2024-09-10T07:00:00Z",
      "finish": "2024-09-17T07:00:00Z",
      "_skip0": null
    },
    "_skip0": null
  },
  {
    "hero_id": "PID_総選挙ルフレ女",
    "active": {
      "start": "2024-09-10T07:00:00Z",
      "finish": "2024-09-17T07:00:00Z",
      "_skip0": null
    },
    "_skip0": null
  },
  {
    "hero_id": "PID_パネトネ",
    "active": {
      "start": "2024-09-10T07:00:00Z",
      "finish": "2024-09-17T07:00:00Z",
      "_skip0": null
    },
    "_skip0": null
  },
  {
    "hero_id": "PID_リョウマ",
    "active": {
      "start": "2024-09-10T07:00:00Z",
      "finish": "2024-09-17T07:00:00Z",
      "_skip0": null
    },
    "_skip0": null
  },
  {
    "hero_id": "PID_リリーナ",
    "active": {
      "start": "2024-09-10T07:00:00Z",
      "finish": "2024-09-17T07:00:00Z",
      "_skip0": null
    },
    "_skip0": null
  },
  {
    "hero_id": "PID_マリス",
    "active": {
      "start": "2024-09-10T07:00:00Z",
      "finish": "2024-09-17T07:00:00Z",
      "_skip0": null
    },
    "_skip0": null
  },
  {
    "hero_id": "PID_シャロン",
    "active": {
      "start": "2024-09-10T07:00:00Z",
      "finish": "2024-09-17T07:00:00Z",
      "_skip0": null
    },
    "_skip0": null
  }
]
